{"selfLink":{"href":"https://services.radio-canada.ca/neuro/v1/lineups/4165?pagenumber=1"},"id":4165,"name":"Science - À la une","template":{"id":75,"name":"01 - Unit - 3 moyenne - 2 petites (1 au-dessus de l'autre)"},"contentItemSummaries":{"firstPageLink":{"href":"https://services.radio-canada.ca/neuro/v1/lineups/4165?pagenumber=1"},"previousPageLink":null,"nextPageLink":{"href":"https://services.radio-canada.ca/neuro/v1/lineups/4165?pagenumber=2"},"lastPageLink":{"href":"https://services.radio-canada.ca/neuro/v1/lineups/4165?pagenumber=2"},"totalNumOfItems":14,"pageNumber":1,"pageSize":10,"items":[{"canonicalWebLink":{"href":"http://ici.radio-canada.ca/nouvelle/1841685/vih-deuxieme-personne-guerie-esperanza-argentine"},"id":1841685,"type":"Nouvelle","title":"Une deuxième personne serait spontanément guérie du VIH","summary":"<p>Certaines personnes possèdent un système immunitaire capable de supprimer le VIH sans médicaments.</p>","summaryImage":{"contentType":{"id":"19","name":"Image (Picto)"},"alt":"Illustration 3D du VIH.","legend":"Illustration 3D du VIH","imageCredits":"","pressAgencies":[{"id":null,"name":"iStock","codeName":"iStock"}],"imageCollection":"","concreteImages":[{"mediaLink":{"href":"https://images.radio-canada.ca/v1/ici-info/1x1/illustration-3d-vih.jpg"},"width":1298,"height":1299,"dimensionRatio":"1:1"},{"mediaLink":{"href":"https://images.radio-canada.ca/v1/ici-info/16x9/illustration-3d-vih.jpg"},"width":2308,"height":1299,"dimensionRatio":"16:9"},{"mediaLink":{"href":"https://images.radio-canada.ca/v1/ici-info/17x6/illustration-3d-vih.jpg"},"width":2308,"height":815,"dimensionRatio":"17:6"},{"mediaLink":{"href":"https://images.radio-canada.ca/v1/ici-info/2x3/illustration-3d-vih.jpg"},"width":865,"height":1299,"dimensionRatio":"2:3"},{"mediaLink":{"href":"https://images.radio-canada.ca/v1/ici-info/4x3/illustration-3d-vih.jpg"},"width":1731,"height":1299,"dimensionRatio":"4:3"},{"mediaLink":{"href":"https://images.radio-canada.ca/v1/ici-info/perso/illustration-3d-vih.jpg"},"width":2308,"height":1299,"dimensionRatio":"perso"}]},"publishedLastTimeAt":"2021-11-22T16:59:30.344Z","template":null,"selfLink":{"href":"https://services.radio-canada.ca/neuro/v1/news-stories/1841685"},"summaryMultimediaItem":{"$type":"RC.Neuro.Dtos.v1.ConceptualImage, RC.Neuro.Dtos","contentType":{"id":"19","name":"Image (Picto)"},"alt":"Illustration 3D du VIH.","legend":"Une illustration 3D représentant le virus de l'immunodéficience humaine (VIH).","imageCredits":"","pressAgencies":[{"id":null,"name":"iStock","codeName":"iStock"}],"imageCollection":"","concreteImages":[{"mediaLink":{"href":"https://images.radio-canada.ca/v1/ici-info/1x1/illustration-3d-vih.jpg"},"width":1298,"height":1299,"dimensionRatio":"1:1"},{"mediaLink":{"href":"https://images.radio-canada.ca/v1/ici-info/16x9/illustration-3d-vih.jpg"},"width":2308,"height":1299,"dimensionRatio":"16:9"},{"mediaLink":{"href":"https://images.radio-canada.ca/v1/ici-info/17x6/illustration-3d-vih.jpg"},"width":2308,"height":815,"dimensionRatio":"17:6"},{"mediaLink":{"href":"https://images.radio-canada.ca/v1/ici-info/2x3/illustration-3d-vih.jpg"},"width":865,"height":1299,"dimensionRatio":"2:3"},{"mediaLink":{"href":"https://images.radio-canada.ca/v1/ici-info/4x3/illustration-3d-vih.jpg"},"width":1731,"height":1299,"dimensionRatio":"4:3"},{"mediaLink":{"href":"https://images.radio-canada.ca/v1/ici-info/perso/illustration-3d-vih.jpg"},"width":2308,"height":1299,"dimensionRatio":"perso"}]},"relatedContents":[],"kicker":"","classificationTag":{"id":12,"name":"Nouvelle","codeName":"nouvelle"},"broadcastableItem":null},{"canonicalWebLink":{"href":"http://ici.radio-canada.ca/nouvelle/1841702/alzheimer-deux-molecules-nouvel-espoir-traitement"},"id":1841702,"type":"Nouvelle","title":"Deux molécules bien connues offrent un nouvel espoir contre l’alzheimer","summary":"<p>Utilisés conjointement, le gemfibrosil et l&#x27;acide rétinoïque pourraient combattre la maladie d&#x27;Alzheimer.</p>","summaryImage":{"contentType":{"id":"19","name":"Image (Picto)"},"alt":"Illustration montrant des neurones présentant des plaques amyloïdes et des neurones sains (à gauche). ","legend":"Neurones présentant des plaques amyloïdes (à droite) comparés à des neurones sains (à gauche). Les plaques amyloïdes s'accumulent à l'extérieur des neurones et  entraînent leur dégénérescence.","imageCredits":"","pressAgencies":[{"id":null,"name":"iStock","codeName":"iStock"}],"imageCollection":"","concreteImages":[{"mediaLink":{"href":"https://images.radio-canada.ca/v1/ici-info/1x1/alzheimer-neurones-plaques-amyloides-illustration.jpg"},"width":2733,"height":2733,"dimensionRatio":"1:1"},{"mediaLink":{"href":"https://images.radio-canada.ca/v1/ici-info/16x9/alzheimer-neurones-plaques-amyloides-illustration.jpg"},"width":3644,"height":2050,"dimensionRatio":"16:9"},{"mediaLink":{"href":"https://images.radio-canada.ca/v1/ici-info/17x6/alzheimer-neurones-plaques-amyloides-illustration.jpg"},"width":3644,"height":1286,"dimensionRatio":"17:6"},{"mediaLink":{"href":"https://images.radio-canada.ca/v1/ici-info/2x3/alzheimer-neurones-plaques-amyloides-illustration.jpg"},"width":1822,"height":2733,"dimensionRatio":"2:3"},{"mediaLink":{"href":"https://images.radio-canada.ca/v1/ici-info/4x3/alzheimer-neurones-plaques-amyloides-illustration.jpg"},"width":3644,"height":2733,"dimensionRatio":"4:3"},{"mediaLink":{"href":"https://images.radio-canada.ca/v1/ici-info/perso/alzheimer-neurones-plaques-amyloides-illustration.jpg"},"width":3644,"height":2733,"dimensionRatio":"perso"}]},"publishedLastTimeAt":"2021-11-22T17:48:27.185Z","template":null,"selfLink":{"href":"https://services.radio-canada.ca/neuro/v1/news-stories/1841702"},"summaryMultimediaItem":{"$type":"RC.Neuro.Dtos.v1.ConceptualImage, RC.Neuro.Dtos","contentType":{"id":"19","name":"Image (Picto)"},"alt":"Illustration montrant des neurones présentant des plaques amyloïdes et des neurones sains (à gauche). ","legend":"Des neurones présentant des plaques amyloïdes (à droite) comparés à des neurones sains (à gauche). Les plaques amyloïdes s'accumulent à l'extérieur des neurones et entraînent leur dégénérescence.","imageCredits":"","pressAgencies":[{"id":null,"name":"iStock","codeName":"iStock"}],"imageCollection":"","concreteImages":[{"mediaLink":{"href":"https://images.radio-canada.ca/v1/ici-info/1x1/alzheimer-neurones-plaques-amyloides-illustration.jpg"},"width":2733,"height":2733,"dimensionRatio":"1:1"},{"mediaLink":{"href":"https://images.radio-canada.ca/v1/ici-info/16x9/alzheimer-neurones-plaques-amyloides-illustration.jpg"},"width":3644,"height":2050,"dimensionRatio":"16:9"},{"mediaLink":{"href":"https://images.radio-canada.ca/v1/ici-info/17x6/alzheimer-neurones-plaques-amyloides-illustration.jpg"},"width":3644,"height":1286,"dimensionRatio":"17:6"},{"mediaLink":{"href":"https://images.radio-canada.ca/v1/ici-info/2x3/alzheimer-neurones-plaques-amyloides-illustration.jpg"},"width":1822,"height":2733,"dimensionRatio":"2:3"},{"mediaLink":{"href":"https://images.radio-canada.ca/v1/ici-info/4x3/alzheimer-neurones-plaques-amyloides-illustration.jpg"},"width":3644,"height":2733,"dimensionRatio":"4:3"},{"mediaLink":{"href":"https://images.radio-canada.ca/v1/ici-info/perso/alzheimer-neurones-plaques-amyloides-illustration.jpg"},"width":3644,"height":2733,"dimensionRatio":"perso"}]},"relatedContents":[],"kicker":"","classificationTag":{"id":12,"name":"Nouvelle","codeName":"nouvelle"},"broadcastableItem":null},{"canonicalWebLink":{"href":"http://ici.radio-canada.ca/nouvelle/1841134/cancer-medicament-tests-chum-essais"},"id":1841134,"type":"Nouvelle","title":"Et si une simple pilule permettait de guérir un cancer?","summary":"<p>Au printemps prochain, des patients du CHUM testeront une pilule expérimentale contre le cancer.</p>","summaryImage":{"contentType":{"id":"19","name":"Image (Picto)"},"alt":"Des pilules.","legend":"Cette pilule viendra-t-elle à bout des cancers?","imageCredits":"","pressAgencies":[{"id":null,"name":"Radio-Canada","codeName":"Radio-Canada"}],"imageCollection":"","concreteImages":[{"mediaLink":{"href":"https://images.radio-canada.ca/v1/ici-info/1x1/cancer-pilule-pclx001.jpg"},"width":1080,"height":1080,"dimensionRatio":"1:1"},{"mediaLink":{"href":"https://images.radio-canada.ca/v1/ici-info/16x9/cancer-pilule-pclx001.jpg"},"width":1920,"height":1080,"dimensionRatio":"16:9"},{"mediaLink":{"href":"https://images.radio-canada.ca/v1/ici-info/17x6/cancer-pilule-pclx001.jpg"},"width":1920,"height":678,"dimensionRatio":"17:6"},{"mediaLink":{"href":"https://images.radio-canada.ca/v1/ici-info/2x3/cancer-pilule-pclx001.jpg"},"width":720,"height":1080,"dimensionRatio":"2:3"},{"mediaLink":{"href":"https://images.radio-canada.ca/v1/ici-info/4x3/cancer-pilule-pclx001.jpg"},"width":1440,"height":1080,"dimensionRatio":"4:3"},{"mediaLink":{"href":"https://images.radio-canada.ca/v1/ici-info/perso/cancer-pilule-pclx001.jpg"},"width":1920,"height":1080,"dimensionRatio":"perso"}]},"publishedLastTimeAt":"2021-11-21T09:02:09.828Z","template":null,"selfLink":{"href":"https://services.radio-canada.ca/neuro/v1/news-stories/1841134"},"summaryMultimediaItem":{"$type":"RC.Neuro.Dtos.v1.ConceptualImage, RC.Neuro.Dtos","contentType":{"id":"19","name":"Image (Picto)"},"alt":"Des pilules.","legend":"Le comprimé PCLX-001 sera mis à l'essai au CHUM au printemps 2022.","imageCredits":"","pressAgencies":[{"id":null,"name":"Radio-Canada","codeName":"Radio-Canada"}],"imageCollection":"","concreteImages":[{"mediaLink":{"href":"https://images.radio-canada.ca/v1/ici-info/1x1/cancer-pilule-pclx001.jpg"},"width":1080,"height":1080,"dimensionRatio":"1:1"},{"mediaLink":{"href":"https://images.radio-canada.ca/v1/ici-info/16x9/cancer-pilule-pclx001.jpg"},"width":1920,"height":1080,"dimensionRatio":"16:9"},{"mediaLink":{"href":"https://images.radio-canada.ca/v1/ici-info/17x6/cancer-pilule-pclx001.jpg"},"width":1920,"height":678,"dimensionRatio":"17:6"},{"mediaLink":{"href":"https://images.radio-canada.ca/v1/ici-info/2x3/cancer-pilule-pclx001.jpg"},"width":720,"height":1080,"dimensionRatio":"2:3"},{"mediaLink":{"href":"https://images.radio-canada.ca/v1/ici-info/4x3/cancer-pilule-pclx001.jpg"},"width":1440,"height":1080,"dimensionRatio":"4:3"},{"mediaLink":{"href":"https://images.radio-canada.ca/v1/ici-info/perso/cancer-pilule-pclx001.jpg"},"width":1920,"height":1080,"dimensionRatio":"perso"}]},"relatedContents":[],"kicker":"","classificationTag":{"id":12,"name":"Nouvelle","codeName":"nouvelle"},"broadcastableItem":null},{"canonicalWebLink":{"href":"http://ici.radio-canada.ca/nouvelle/1840967/bresil-nouvelle-espece-dinosaure-sans-dents-berthasaura-leopoldinae"},"id":1840967,"type":"Nouvelle","title":"Une nouvelle espèce de dinosaure sans dents découverte au Brésil","summary":"<p>Le théropode vivait dans le sud du Brésil il y a 70 à 80&nbsp;millions d&#x27;années.</p>","summaryImage":{"contentType":{"id":"19","name":"Image (Picto)"},"alt":"Illustraion d'un Berthasaura leopoldinae dans son milieu naturel.","legend":"Le Berthasaura leopoldinae est le premier théropode sans dents connu.","imageCredits":"Museu Nacional/Universidade Federal do Rio de Janeiro","pressAgencies":[],"imageCollection":"","concreteImages":[{"mediaLink":{"href":"https://images.radio-canada.ca/v1/ici-info/1x1/dinosaure-bresil-berthasaura-leopoldinae-illustration.jpeg"},"width":845,"height":845,"dimensionRatio":"1:1"},{"mediaLink":{"href":"https://images.radio-canada.ca/v1/ici-info/16x9/dinosaure-bresil-berthasaura-leopoldinae-illustration.jpeg"},"width":1200,"height":675,"dimensionRatio":"16:9"},{"mediaLink":{"href":"https://images.radio-canada.ca/v1/ici-info/17x6/dinosaure-bresil-berthasaura-leopoldinae-illustration.jpeg"},"width":1200,"height":424,"dimensionRatio":"17:6"},{"mediaLink":{"href":"https://images.radio-canada.ca/v1/ici-info/2x3/dinosaure-bresil-berthasaura-leopoldinae-illustration.jpeg"},"width":563,"height":845,"dimensionRatio":"2:3"},{"mediaLink":{"href":"https://images.radio-canada.ca/v1/ici-info/4x3/dinosaure-bresil-berthasaura-leopoldinae-illustration.jpeg"},"width":1127,"height":845,"dimensionRatio":"4:3"},{"mediaLink":{"href":"https://images.radio-canada.ca/v1/ici-info/perso/dinosaure-bresil-berthasaura-leopoldinae-illustration.jpeg"},"width":1200,"height":845,"dimensionRatio":"perso"}]},"publishedLastTimeAt":"2021-11-18T21:23:03.151Z","template":null,"selfLink":{"href":"https://services.radio-canada.ca/neuro/v1/news-stories/1840967"},"summaryMultimediaItem":{"$type":"RC.Neuro.Dtos.v1.ConceptualImage, RC.Neuro.Dtos","contentType":{"id":"19","name":"Image (Picto)"},"alt":"Illustraion d'un Berthasaura leopoldinae dans son milieu naturel.","legend":"Le Berthasaura leopoldinae est le premier théropode sans dents connu.","imageCredits":"Museu Nacional/Universidade Federal do Rio de Janeiro","pressAgencies":[],"imageCollection":"","concreteImages":[{"mediaLink":{"href":"https://images.radio-canada.ca/v1/ici-info/1x1/dinosaure-bresil-berthasaura-leopoldinae-illustration.jpeg"},"width":845,"height":845,"dimensionRatio":"1:1"},{"mediaLink":{"href":"https://images.radio-canada.ca/v1/ici-info/16x9/dinosaure-bresil-berthasaura-leopoldinae-illustration.jpeg"},"width":1200,"height":675,"dimensionRatio":"16:9"},{"mediaLink":{"href":"https://images.radio-canada.ca/v1/ici-info/17x6/dinosaure-bresil-berthasaura-leopoldinae-illustration.jpeg"},"width":1200,"height":424,"dimensionRatio":"17:6"},{"mediaLink":{"href":"https://images.radio-canada.ca/v1/ici-info/2x3/dinosaure-bresil-berthasaura-leopoldinae-illustration.jpeg"},"width":563,"height":845,"dimensionRatio":"2:3"},{"mediaLink":{"href":"https://images.radio-canada.ca/v1/ici-info/4x3/dinosaure-bresil-berthasaura-leopoldinae-illustration.jpeg"},"width":1127,"height":845,"dimensionRatio":"4:3"},{"mediaLink":{"href":"https://images.radio-canada.ca/v1/ici-info/perso/dinosaure-bresil-berthasaura-leopoldinae-illustration.jpeg"},"width":1200,"height":845,"dimensionRatio":"perso"}]},"relatedContents":[],"kicker":"","classificationTag":{"id":12,"name":"Nouvelle","codeName":"nouvelle"},"broadcastableItem":null},{"canonicalWebLink":{"href":"http://ici.radio-canada.ca/nouvelle/1840934/eclipse-lune-quasi-totale-la-plus-longue-depuis-1440"},"id":1840934,"type":"Nouvelle","title":"Éclipse de Lune «&nbsp;quasi totale&nbsp;», la plus longue depuis 1440","summary":"<p>Au plus fort, 97,4&nbsp;% de la surface visible de la Lune a été masquée.</p>","summaryImage":{"contentType":{"id":"19","name":"Image (Picto)"},"alt":"L'éclipse visible dans le ciel de Tokyo, au Japon.","legend":"L'éclipse partielle dans le ciel de Tokyo, au Japon.","imageCredits":"Issei Kato","pressAgencies":[{"id":null,"name":"Reuters","codeName":"Reuters"}],"imageCollection":"","concreteImages":[{"mediaLink":{"href":"https://images.radio-canada.ca/v1/ici-info/1x1/eclipse-partielle-tokyo-japon.JPG"},"width":1388,"height":1388,"dimensionRatio":"1:1"},{"mediaLink":{"href":"https://images.radio-canada.ca/v1/ici-info/16x9/eclipse-partielle-tokyo-japon.JPG"},"width":1944,"height":1094,"dimensionRatio":"16:9"},{"mediaLink":{"href":"https://images.radio-canada.ca/v1/ici-info/17x6/eclipse-partielle-tokyo-japon.JPG"},"width":1944,"height":686,"dimensionRatio":"17:6"},{"mediaLink":{"href":"https://images.radio-canada.ca/v1/ici-info/2x3/eclipse-partielle-tokyo-japon.JPG"},"width":752,"height":1129,"dimensionRatio":"2:3"},{"mediaLink":{"href":"https://images.radio-canada.ca/v1/ici-info/4x3/eclipse-partielle-tokyo-japon.JPG"},"width":874,"height":655,"dimensionRatio":"4:3"},{"mediaLink":{"href":"https://images.radio-canada.ca/v1/ici-info/perso/eclipse-partielle-tokyo-japon.JPG"},"width":1944,"height":1388,"dimensionRatio":"perso"}]},"publishedLastTimeAt":"2021-11-18T20:21:29.834Z","template":null,"selfLink":{"href":"https://services.radio-canada.ca/neuro/v1/news-stories/1840934"},"summaryMultimediaItem":{"$type":"RC.Neuro.Dtos.v1.ConceptualImage, RC.Neuro.Dtos","contentType":{"id":"19","name":"Image (Picto)"},"alt":"L'éclipse visible dans le ciel de Tokyo, au Japon.","legend":"L'éclipse partielle dans le ciel de Tokyo, au Japon.","imageCredits":"Issei Kato","pressAgencies":[{"id":null,"name":"Reuters","codeName":"Reuters"}],"imageCollection":"","concreteImages":[{"mediaLink":{"href":"https://images.radio-canada.ca/v1/ici-info/1x1/eclipse-partielle-tokyo-japon.JPG"},"width":1388,"height":1388,"dimensionRatio":"1:1"},{"mediaLink":{"href":"https://images.radio-canada.ca/v1/ici-info/16x9/eclipse-partielle-tokyo-japon.JPG"},"width":1944,"height":1094,"dimensionRatio":"16:9"},{"mediaLink":{"href":"https://images.radio-canada.ca/v1/ici-info/17x6/eclipse-partielle-tokyo-japon.JPG"},"width":1944,"height":686,"dimensionRatio":"17:6"},{"mediaLink":{"href":"https://images.radio-canada.ca/v1/ici-info/2x3/eclipse-partielle-tokyo-japon.JPG"},"width":752,"height":1129,"dimensionRatio":"2:3"},{"mediaLink":{"href":"https://images.radio-canada.ca/v1/ici-info/4x3/eclipse-partielle-tokyo-japon.JPG"},"width":874,"height":655,"dimensionRatio":"4:3"},{"mediaLink":{"href":"https://images.radio-canada.ca/v1/ici-info/perso/eclipse-partielle-tokyo-japon.JPG"},"width":1944,"height":1388,"dimensionRatio":"perso"}]},"relatedContents":[],"kicker":"","classificationTag":{"id":12,"name":"Nouvelle","codeName":"nouvelle"},"broadcastableItem":null},{"canonicalWebLink":{"href":"http://ici.radio-canada.ca/nouvelle/1840880/maroc-decouverte-parures-anciennes-monde"},"id":1840880,"type":"Nouvelle","title":"Découverte au Maroc de parures présentées comme «&nbsp;les plus anciennes au monde&nbsp;»","summary":"<p>Des colliers et des bracelets formés de petits coquillages ont été trouvés dans la grotte de Bizmoune.</p>","summaryImage":{"contentType":{"id":"19","name":"Image (Picto)"},"alt":"Éléments de parures.","legend":"Éléments de parures découverts dans la grotte de Bizmoune, près d'Essaouira.","imageCredits":"INSAP/A. Bouzouggar","pressAgencies":[],"imageCollection":"","concreteImages":[{"mediaLink":{"href":"https://images.radio-canada.ca/v1/ici-info/1x1/maroc-bizmoune-anciennes-parures-elements-.jpg"},"width":3011,"height":3011,"dimensionRatio":"1:1"},{"mediaLink":{"href":"https://images.radio-canada.ca/v1/ici-info/16x9/maroc-bizmoune-anciennes-parures-elements-.jpg"},"width":3011,"height":1694,"dimensionRatio":"16:9"},{"mediaLink":{"href":"https://images.radio-canada.ca/v1/ici-info/17x6/maroc-bizmoune-anciennes-parures-elements-.jpg"},"width":3011,"height":1063,"dimensionRatio":"17:6"},{"mediaLink":{"href":"https://images.radio-canada.ca/v1/ici-info/2x3/maroc-bizmoune-anciennes-parures-elements-.jpg"},"width":2020,"height":3030,"dimensionRatio":"2:3"},{"mediaLink":{"href":"https://images.radio-canada.ca/v1/ici-info/4x3/maroc-bizmoune-anciennes-parures-elements-.jpg"},"width":2909,"height":2182,"dimensionRatio":"4:3"},{"mediaLink":{"href":"https://images.radio-canada.ca/v1/ici-info/perso/maroc-bizmoune-anciennes-parures-elements-.jpg"},"width":3011,"height":3030,"dimensionRatio":"perso"}]},"publishedLastTimeAt":"2021-11-18T18:20:01.968Z","template":null,"selfLink":{"href":"https://services.radio-canada.ca/neuro/v1/news-stories/1840880"},"summaryMultimediaItem":{"$type":"RC.Neuro.Dtos.v1.ConceptualImage, RC.Neuro.Dtos","contentType":{"id":"19","name":"Image (Picto)"},"alt":"Éléments de parures.","legend":"Éléments de parures découverts dans la grotte de Bizmoune, près d'Essaouira.","imageCredits":"INSAP/A. Bouzouggar","pressAgencies":[],"imageCollection":"","concreteImages":[{"mediaLink":{"href":"https://images.radio-canada.ca/v1/ici-info/1x1/maroc-bizmoune-anciennes-parures-elements-.jpg"},"width":3011,"height":3011,"dimensionRatio":"1:1"},{"mediaLink":{"href":"https://images.radio-canada.ca/v1/ici-info/16x9/maroc-bizmoune-anciennes-parures-elements-.jpg"},"width":3011,"height":1694,"dimensionRatio":"16:9"},{"mediaLink":{"href":"https://images.radio-canada.ca/v1/ici-info/17x6/maroc-bizmoune-anciennes-parures-elements-.jpg"},"width":3011,"height":1063,"dimensionRatio":"17:6"},{"mediaLink":{"href":"https://images.radio-canada.ca/v1/ici-info/2x3/maroc-bizmoune-anciennes-parures-elements-.jpg"},"width":2020,"height":3030,"dimensionRatio":"2:3"},{"mediaLink":{"href":"https://images.radio-canada.ca/v1/ici-info/4x3/maroc-bizmoune-anciennes-parures-elements-.jpg"},"width":2909,"height":2182,"dimensionRatio":"4:3"},{"mediaLink":{"href":"https://images.radio-canada.ca/v1/ici-info/perso/maroc-bizmoune-anciennes-parures-elements-.jpg"},"width":3011,"height":3030,"dimensionRatio":"perso"}]},"relatedContents":[],"kicker":"","classificationTag":{"id":12,"name":"Nouvelle","codeName":"nouvelle"},"broadcastableItem":null},{"canonicalWebLink":{"href":"http://ici.radio-canada.ca/nouvelle/1840791/linguistique-effet-bouba-kiki-confirmation-20-langues"},"id":1840791,"type":"Nouvelle","title":"L’effet «&nbsp;bouba/kiki&nbsp;» confirmé dans plus de 20 langues","summary":"<p>Les chercheurs ont testé plus de 900&nbsp;locuteurs de neuf familles de langues.</p>","summaryImage":{"contentType":{"id":"19","name":"Image (Picto)"},"alt":"Personnages avec des nuages de commentaires au-dessus de leur tête. ","legend":"Une forte proportion de mots de base dans plus de 4000 langues partagent des sons spécifiques.","imageCredits":"Andrii Yalanskyi","pressAgencies":[{"id":null,"name":"iStock","codeName":"iStock"}],"imageCollection":"","concreteImages":[{"mediaLink":{"href":"https://images.radio-canada.ca/v1/ici-info/1x1/langues-parole-concept.jpg"},"width":1361,"height":1361,"dimensionRatio":"1:1"},{"mediaLink":{"href":"https://images.radio-canada.ca/v1/ici-info/16x9/langues-parole-concept.jpg"},"width":2201,"height":1238,"dimensionRatio":"16:9"},{"mediaLink":{"href":"https://images.radio-canada.ca/v1/ici-info/17x6/langues-parole-concept.jpg"},"width":2201,"height":777,"dimensionRatio":"17:6"},{"mediaLink":{"href":"https://images.radio-canada.ca/v1/ici-info/2x3/langues-parole-concept.jpg"},"width":907,"height":1361,"dimensionRatio":"2:3"},{"mediaLink":{"href":"https://images.radio-canada.ca/v1/ici-info/4x3/langues-parole-concept.jpg"},"width":1619,"height":1214,"dimensionRatio":"4:3"},{"mediaLink":{"href":"https://images.radio-canada.ca/v1/ici-info/perso/langues-parole-concept.jpg"},"width":2201,"height":1361,"dimensionRatio":"perso"}]},"publishedLastTimeAt":"2021-11-18T15:14:34.083Z","template":null,"selfLink":{"href":"https://services.radio-canada.ca/neuro/v1/news-stories/1840791"},"summaryMultimediaItem":{"$type":"RC.Neuro.Dtos.v1.ConceptualImage, RC.Neuro.Dtos","contentType":{"id":"19","name":"Image (Picto)"},"alt":"Personnages avec des nuages de commentaires au-dessus de leur tête. ","legend":"Une forte proportion de mots de base dans plus de 4000 langues partagent des sons spécifiques.","imageCredits":"Andrii Yalanskyi","pressAgencies":[{"id":null,"name":"iStock","codeName":"iStock"}],"imageCollection":"","concreteImages":[{"mediaLink":{"href":"https://images.radio-canada.ca/v1/ici-info/1x1/langues-parole-concept.jpg"},"width":1361,"height":1361,"dimensionRatio":"1:1"},{"mediaLink":{"href":"https://images.radio-canada.ca/v1/ici-info/16x9/langues-parole-concept.jpg"},"width":2201,"height":1238,"dimensionRatio":"16:9"},{"mediaLink":{"href":"https://images.radio-canada.ca/v1/ici-info/17x6/langues-parole-concept.jpg"},"width":2201,"height":777,"dimensionRatio":"17:6"},{"mediaLink":{"href":"https://images.radio-canada.ca/v1/ici-info/2x3/langues-parole-concept.jpg"},"width":907,"height":1361,"dimensionRatio":"2:3"},{"mediaLink":{"href":"https://images.radio-canada.ca/v1/ici-info/4x3/langues-parole-concept.jpg"},"width":1619,"height":1214,"dimensionRatio":"4:3"},{"mediaLink":{"href":"https://images.radio-canada.ca/v1/ici-info/perso/langues-parole-concept.jpg"},"width":2201,"height":1361,"dimensionRatio":"perso"}]},"relatedContents":[],"kicker":"","classificationTag":{"id":12,"name":"Nouvelle","codeName":"nouvelle"},"broadcastableItem":null},{"canonicalWebLink":{"href":"http://ici.radio-canada.ca/nouvelle/1840695/grand-meres-role-lien-intergenerationnel-apercu-neurologique"},"id":1840695,"type":"Nouvelle","title":"C’est officiel&nbsp;: les grands-mères sont scientifiquement bonnes pour vous","summary":"<p>Une nouvelle étude révèle pour la première fois un aperçu neurologique de ce lien intergénérationnel.</p>","summaryImage":{"contentType":{"id":"19","name":"Image (Picto)"},"alt":"Un jeune garçon se fait prendre dans les bras de sa grand-mère.","legend":"La présence physique, grande victime de la COVID-19, est très importante pour de nombreuses personnes.","imageCredits":"","pressAgencies":[{"id":null,"name":"iStock","codeName":"iStock"}],"imageCollection":"","concreteImages":[{"mediaLink":{"href":"https://images.radio-canada.ca/v1/ici-premiere/1x1/calin-enfant-aine.JPG"},"width":533,"height":533,"dimensionRatio":"1:1"},{"mediaLink":{"href":"https://images.radio-canada.ca/v1/ici-premiere/16x9/calin-enfant-aine.JPG"},"width":947,"height":533,"dimensionRatio":"16:9"},{"mediaLink":{"href":"https://images.radio-canada.ca/v1/ici-premiere/17x6/calin-enfant-aine.JPG"},"width":947,"height":334,"dimensionRatio":"17:6"},{"mediaLink":{"href":"https://images.radio-canada.ca/v1/ici-premiere/2x3/calin-enfant-aine.JPG"},"width":355,"height":533,"dimensionRatio":"2:3"},{"mediaLink":{"href":"https://images.radio-canada.ca/v1/ici-premiere/4x3/calin-enfant-aine.JPG"},"width":711,"height":533,"dimensionRatio":"4:3"},{"mediaLink":{"href":"https://images.radio-canada.ca/v1/ici-premiere/perso/calin-enfant-aine.JPG"},"width":947,"height":533,"dimensionRatio":"perso"}]},"publishedLastTimeAt":"2021-11-17T22:25:11.541Z","template":null,"selfLink":{"href":"https://services.radio-canada.ca/neuro/v1/news-stories/1840695"},"summaryMultimediaItem":{"$type":"RC.Neuro.Dtos.v1.ConceptualImage, RC.Neuro.Dtos","contentType":{"id":"19","name":"Image (Picto)"},"alt":"Une grand-mère prend son petit-fils dans ses bras.","legend":"L'étude révèle pour la première fois un aperçu neurologique du lien intergénérationnel.","imageCredits":"","pressAgencies":[{"id":null,"name":"iStock","codeName":"iStock"}],"imageCollection":"","concreteImages":[{"mediaLink":{"href":"https://images.radio-canada.ca/v1/ici-premiere/1x1/calin-enfant-aine.JPG"},"width":533,"height":533,"dimensionRatio":"1:1"},{"mediaLink":{"href":"https://images.radio-canada.ca/v1/ici-premiere/16x9/calin-enfant-aine.JPG"},"width":947,"height":533,"dimensionRatio":"16:9"},{"mediaLink":{"href":"https://images.radio-canada.ca/v1/ici-premiere/17x6/calin-enfant-aine.JPG"},"width":947,"height":334,"dimensionRatio":"17:6"},{"mediaLink":{"href":"https://images.radio-canada.ca/v1/ici-premiere/2x3/calin-enfant-aine.JPG"},"width":355,"height":533,"dimensionRatio":"2:3"},{"mediaLink":{"href":"https://images.radio-canada.ca/v1/ici-premiere/4x3/calin-enfant-aine.JPG"},"width":711,"height":533,"dimensionRatio":"4:3"},{"mediaLink":{"href":"https://images.radio-canada.ca/v1/ici-premiere/perso/calin-enfant-aine.JPG"},"width":947,"height":533,"dimensionRatio":"perso"}]},"relatedContents":[],"kicker":"","classificationTag":{"id":12,"name":"Nouvelle","codeName":"nouvelle"},"broadcastableItem":null},{"canonicalWebLink":{"href":"http://ici.radio-canada.ca/nouvelle/1840523/sajeev-john-physique-optique-medaille-gerhard-herzberg"},"id":1840523,"type":"Nouvelle","title":"Un physicien qui a réussi à capturer la lumière gagne un prix d’un million&nbsp;$","summary":"<p>En plus de ses applications médicales, son invention pourrait aider à combattre les changements climatiques.</p>","summaryImage":{"contentType":{"id":"19","name":"Image (Picto)"},"alt":"Sajeev John, bras croisés, se tient à l'extérieur d'un édifice.","legend":"Sajeev John, 64 ans, est né en Inde et il a grandi à Ottawa et à London, en Ontario. \n","imageCredits":"Sylvie Li","pressAgencies":[{"id":null,"name":"CBC","codeName":"CBC"}],"imageCollection":"","concreteImages":[{"mediaLink":{"href":"https://images.radio-canada.ca/v1/ici-info/1x1/sajeev-john-toronto-physique-optique-science-8074.jpg"},"width":853,"height":853,"dimensionRatio":"1:1"},{"mediaLink":{"href":"https://images.radio-canada.ca/v1/ici-info/16x9/sajeev-john-toronto-physique-optique-science-8074.jpg"},"width":1280,"height":720,"dimensionRatio":"16:9"},{"mediaLink":{"href":"https://images.radio-canada.ca/v1/ici-info/17x6/sajeev-john-toronto-physique-optique-science-8074.jpg"},"width":1280,"height":452,"dimensionRatio":"17:6"},{"mediaLink":{"href":"https://images.radio-canada.ca/v1/ici-info/2x3/sajeev-john-toronto-physique-optique-science-8074.jpg"},"width":568,"height":852,"dimensionRatio":"2:3"},{"mediaLink":{"href":"https://images.radio-canada.ca/v1/ici-info/4x3/sajeev-john-toronto-physique-optique-science-8074.jpg"},"width":1137,"height":853,"dimensionRatio":"4:3"},{"mediaLink":{"href":"https://images.radio-canada.ca/v1/ici-info/perso/sajeev-john-toronto-physique-optique-science-8074.jpg"},"width":1280,"height":853,"dimensionRatio":"perso"}]},"publishedLastTimeAt":"2021-11-17T16:14:12.447Z","template":null,"selfLink":{"href":"https://services.radio-canada.ca/neuro/v1/news-stories/1840523"},"summaryMultimediaItem":{"$type":"RC.Neuro.Dtos.v1.ConceptualImage, RC.Neuro.Dtos","contentType":{"id":"19","name":"Image (Picto)"},"alt":"Sajeev John, bras croisés, se tient à l'extérieur d'un édifice.","legend":"Sajeev John, 64 ans, est né en Inde et il a grandi à Ottawa et à London, en Ontario. \n","imageCredits":"Sylvie Li","pressAgencies":[{"id":null,"name":"CBC","codeName":"CBC"}],"imageCollection":"","concreteImages":[{"mediaLink":{"href":"https://images.radio-canada.ca/v1/ici-info/1x1/sajeev-john-toronto-physique-optique-science-8074.jpg"},"width":853,"height":853,"dimensionRatio":"1:1"},{"mediaLink":{"href":"https://images.radio-canada.ca/v1/ici-info/16x9/sajeev-john-toronto-physique-optique-science-8074.jpg"},"width":1280,"height":720,"dimensionRatio":"16:9"},{"mediaLink":{"href":"https://images.radio-canada.ca/v1/ici-info/17x6/sajeev-john-toronto-physique-optique-science-8074.jpg"},"width":1280,"height":452,"dimensionRatio":"17:6"},{"mediaLink":{"href":"https://images.radio-canada.ca/v1/ici-info/2x3/sajeev-john-toronto-physique-optique-science-8074.jpg"},"width":568,"height":852,"dimensionRatio":"2:3"},{"mediaLink":{"href":"https://images.radio-canada.ca/v1/ici-info/4x3/sajeev-john-toronto-physique-optique-science-8074.jpg"},"width":1137,"height":853,"dimensionRatio":"4:3"},{"mediaLink":{"href":"https://images.radio-canada.ca/v1/ici-info/perso/sajeev-john-toronto-physique-optique-science-8074.jpg"},"width":1280,"height":853,"dimensionRatio":"perso"}]},"relatedContents":[],"kicker":"","classificationTag":{"id":12,"name":"Nouvelle","codeName":"nouvelle"},"broadcastableItem":null},{"canonicalWebLink":{"href":"http://ici.radio-canada.ca/nouvelle/1840503/phages-bacteries-resistantes-antibiotiques"},"id":1840503,"type":"Nouvelle","title":"Les phages, de puissants tueurs à l’assaut des bactéries résistantes","summary":"<p>Les phages sont une piste prise très au sérieux dans la lutte contre la résistance aux antibiotiques.</p>","summaryImage":{"contentType":{"id":"19","name":"Image (Picto)"},"alt":"Un chercheur montre une boîte de Petri remplie des phages nécessaires pour combattre une bactérie.","legend":"Un chercheur montre une boîte de Petri remplie des phages nécessaires pour combattre une bactérie dans le laboratoire de Pherecydes Pharma, en France.","imageCredits":"Julien de Rosa","pressAgencies":[{"id":null,"name":"Getty Images","codeName":"Getty Images"}],"imageCollection":"","concreteImages":[{"mediaLink":{"href":"https://images.radio-canada.ca/v1/ici-info/1x1/phages-boite-petri-laboratoire.jpg"},"width":3712,"height":3712,"dimensionRatio":"1:1"},{"mediaLink":{"href":"https://images.radio-canada.ca/v1/ici-info/16x9/phages-boite-petri-laboratoire.jpg"},"width":5568,"height":3132,"dimensionRatio":"16:9"},{"mediaLink":{"href":"https://images.radio-canada.ca/v1/ici-info/17x6/phages-boite-petri-laboratoire.jpg"},"width":5568,"height":1965,"dimensionRatio":"17:6"},{"mediaLink":{"href":"https://images.radio-canada.ca/v1/ici-info/2x3/phages-boite-petri-laboratoire.jpg"},"width":2474,"height":3711,"dimensionRatio":"2:3"},{"mediaLink":{"href":"https://images.radio-canada.ca/v1/ici-info/4x3/phages-boite-petri-laboratoire.jpg"},"width":4949,"height":3712,"dimensionRatio":"4:3"},{"mediaLink":{"href":"https://images.radio-canada.ca/v1/ici-info/perso/phages-boite-petri-laboratoire.jpg"},"width":5568,"height":3712,"dimensionRatio":"perso"}]},"publishedLastTimeAt":"2021-11-17T14:59:01.382Z","template":null,"selfLink":{"href":"https://services.radio-canada.ca/neuro/v1/news-stories/1840503"},"summaryMultimediaItem":{"$type":"RC.Neuro.Dtos.v1.ConceptualImage, RC.Neuro.Dtos","contentType":{"id":"19","name":"Image (Picto)"},"alt":"Un chercheur montre une boîte de Petri remplie des phages nécessaires pour combattre une bactérie.","legend":"Un chercheur montre une boîte de Petri remplie des phages nécessaires pour combattre une bactérie dans le laboratoire de Pherecydes Pharma, en France.","imageCredits":"Julien de Rosa","pressAgencies":[{"id":null,"name":"Getty Images","codeName":"Getty Images"}],"imageCollection":"","concreteImages":[{"mediaLink":{"href":"https://images.radio-canada.ca/v1/ici-info/1x1/phages-boite-petri-laboratoire.jpg"},"width":3712,"height":3712,"dimensionRatio":"1:1"},{"mediaLink":{"href":"https://images.radio-canada.ca/v1/ici-info/16x9/phages-boite-petri-laboratoire.jpg"},"width":5568,"height":3132,"dimensionRatio":"16:9"},{"mediaLink":{"href":"https://images.radio-canada.ca/v1/ici-info/17x6/phages-boite-petri-laboratoire.jpg"},"width":5568,"height":1965,"dimensionRatio":"17:6"},{"mediaLink":{"href":"https://images.radio-canada.ca/v1/ici-info/2x3/phages-boite-petri-laboratoire.jpg"},"width":2474,"height":3711,"dimensionRatio":"2:3"},{"mediaLink":{"href":"https://images.radio-canada.ca/v1/ici-info/4x3/phages-boite-petri-laboratoire.jpg"},"width":4949,"height":3712,"dimensionRatio":"4:3"},{"mediaLink":{"href":"https://images.radio-canada.ca/v1/ici-info/perso/phages-boite-petri-laboratoire.jpg"},"width":5568,"height":3712,"dimensionRatio":"perso"}]},"relatedContents":[],"kicker":"","classificationTag":{"id":12,"name":"Nouvelle","codeName":"nouvelle"},"broadcastableItem":null}]}}