{"selfLink":{"href":"https://services.radio-canada.ca/neuro/v1/lineups/4159?pagenumber=1"},"id":4159,"name":"0 PPage - Nouvelles","template":{"id":102,"name":"01 - Unit - Bloc à la une - Info"},"contentItemSummaries":{"firstPageLink":{"href":"https://services.radio-canada.ca/neuro/v1/lineups/4159?pagenumber=1"},"previousPageLink":null,"nextPageLink":{"href":"https://services.radio-canada.ca/neuro/v1/lineups/4159?pagenumber=2"},"lastPageLink":{"href":"https://services.radio-canada.ca/neuro/v1/lineups/4159?pagenumber=3"},"totalNumOfItems":28,"pageNumber":1,"pageSize":10,"items":[{"canonicalWebLink":{"href":"http://ici.radio-canada.ca/nouvelle/1850302/covid-ontario-omicron-coronavirus-sante"},"id":1850302,"type":"Nouvelle","title":"COVID-19&nbsp;: plus de 9800&nbsp;nouveaux cas en Ontario","summary":"<p>L’Ontario signale 9826&nbsp;nouveaux cas de COVID-19. </p>","summaryImage":{"contentType":{"id":"19","name":"Image (Picto)"},"alt":"Une main qui présente un écouvillon utilisé pour les prélèvements du test de coronavirus. ","legend":"Il y a sept nouveaux cas de coronavirus dans l'Est de l'Ontario.","imageCredits":"Paul Chiasson","pressAgencies":[{"id":null,"name":"La Presse canadienne","codeName":"La Presse canadienne"}],"imageCollection":"","concreteImages":[{"mediaLink":{"href":"https://images.radio-canada.ca/v1/ici-info/1x1/test-diagnostic-coronavirus-covid-19-4.jpg"},"width":2946,"height":2946,"dimensionRatio":"1:1"},{"mediaLink":{"href":"https://images.radio-canada.ca/v1/ici-info/16x9/test-diagnostic-coronavirus-covid-19-4.jpg"},"width":4750,"height":2672,"dimensionRatio":"16:9"},{"mediaLink":{"href":"https://images.radio-canada.ca/v1/ici-info/17x6/test-diagnostic-coronavirus-covid-19-4.jpg"},"width":4750,"height":1676,"dimensionRatio":"17:6"},{"mediaLink":{"href":"https://images.radio-canada.ca/v1/ici-info/2x3/test-diagnostic-coronavirus-covid-19-4.jpg"},"width":1964,"height":2946,"dimensionRatio":"2:3"},{"mediaLink":{"href":"https://images.radio-canada.ca/v1/ici-info/4x3/test-diagnostic-coronavirus-covid-19-4.jpg"},"width":3928,"height":2946,"dimensionRatio":"4:3"},{"mediaLink":{"href":"https://images.radio-canada.ca/v1/ici-info/perso/test-diagnostic-coronavirus-covid-19-4.jpg"},"width":4750,"height":2946,"dimensionRatio":"perso"}]},"publishedLastTimeAt":"2021-12-26T16:08:52.477Z","template":null,"selfLink":{"href":"https://services.radio-canada.ca/neuro/v1/news-stories/1850302"},"summaryMultimediaItem":{"$type":"RC.Neuro.Dtos.v1.ConceptualImage, RC.Neuro.Dtos","contentType":{"id":"19","name":"Image (Picto)"},"alt":"Une main qui présente un écouvillon utilisé pour les prélèvements du test de coronavirus. ","legend":"Selon la ministre de la Santé de l'Ontario, la province a enregistré 9826 nouvelles infections dimanche.","imageCredits":"Paul Chiasson","pressAgencies":[{"id":null,"name":"La Presse canadienne","codeName":"La Presse canadienne"}],"imageCollection":"","concreteImages":[{"mediaLink":{"href":"https://images.radio-canada.ca/v1/ici-info/1x1/test-diagnostic-coronavirus-covid-19-4.jpg"},"width":2946,"height":2946,"dimensionRatio":"1:1"},{"mediaLink":{"href":"https://images.radio-canada.ca/v1/ici-info/16x9/test-diagnostic-coronavirus-covid-19-4.jpg"},"width":4750,"height":2672,"dimensionRatio":"16:9"},{"mediaLink":{"href":"https://images.radio-canada.ca/v1/ici-info/17x6/test-diagnostic-coronavirus-covid-19-4.jpg"},"width":4750,"height":1676,"dimensionRatio":"17:6"},{"mediaLink":{"href":"https://images.radio-canada.ca/v1/ici-info/2x3/test-diagnostic-coronavirus-covid-19-4.jpg"},"width":1964,"height":2946,"dimensionRatio":"2:3"},{"mediaLink":{"href":"https://images.radio-canada.ca/v1/ici-info/4x3/test-diagnostic-coronavirus-covid-19-4.jpg"},"width":3928,"height":2946,"dimensionRatio":"4:3"},{"mediaLink":{"href":"https://images.radio-canada.ca/v1/ici-info/perso/test-diagnostic-coronavirus-covid-19-4.jpg"},"width":4750,"height":2946,"dimensionRatio":"perso"}]},"relatedContents":[],"kicker":"","classificationTag":{"id":12,"name":"Nouvelle","codeName":"nouvelle"},"broadcastableItem":null},{"canonicalWebLink":{"href":"http://ici.radio-canada.ca/nouvelle/1850299/restrictions-coronavirus-covid-variant-omicron-quebec-26-decembre"},"id":1850299,"type":"Nouvelle","title":"Les rassemblements privés sont désormais limités à six personnes au Québec","summary":"<p>Un maximum de deux personnes par jour peuvent visiter un proche dans une résidence privée pour aînés.</p>","summaryImage":{"contentType":{"id":"19","name":"Image (Picto)"},"alt":"Une personne fait son jogging dans un parc, le long du fleuve Saint-Laurent.","legend":"Les Québécois ont droit à un temps des Fêtes hors de l'ordinaire, alors que les contacts doivent être limités pour éviter la propagation de la COVID-19.","imageCredits":"Graham Hughes","pressAgencies":[{"id":null,"name":"La Presse canadienne","codeName":"La Presse canadienne"}],"imageCollection":"","concreteImages":[{"mediaLink":{"href":"https://images.radio-canada.ca/v1/ici-info/1x1/montreal-jogging-hiver-saint-laurent.JPG"},"width":2070,"height":2070,"dimensionRatio":"1:1"},{"mediaLink":{"href":"https://images.radio-canada.ca/v1/ici-info/16x9/montreal-jogging-hiver-saint-laurent.JPG"},"width":3000,"height":1688,"dimensionRatio":"16:9"},{"mediaLink":{"href":"https://images.radio-canada.ca/v1/ici-info/17x6/montreal-jogging-hiver-saint-laurent.JPG"},"width":3000,"height":1059,"dimensionRatio":"17:6"},{"mediaLink":{"href":"https://images.radio-canada.ca/v1/ici-info/2x3/montreal-jogging-hiver-saint-laurent.JPG"},"width":1380,"height":2070,"dimensionRatio":"2:3"},{"mediaLink":{"href":"https://images.radio-canada.ca/v1/ici-info/4x3/montreal-jogging-hiver-saint-laurent.JPG"},"width":2760,"height":2070,"dimensionRatio":"4:3"},{"mediaLink":{"href":"https://images.radio-canada.ca/v1/ici-info/perso/montreal-jogging-hiver-saint-laurent.JPG"},"width":3000,"height":2070,"dimensionRatio":"perso"}]},"publishedLastTimeAt":"2021-12-26T13:33:14.850Z","template":null,"selfLink":{"href":"https://services.radio-canada.ca/neuro/v1/news-stories/1850299"},"summaryMultimediaItem":{"$type":"RC.Neuro.Dtos.v1.ConceptualImage, RC.Neuro.Dtos","contentType":{"id":"19","name":"Image (Picto)"},"alt":"Une personne fait son jogging dans un parc le long du fleuve Saint-Laurent.","legend":"Les Québécois ont droit à un temps des Fêtes hors de l'ordinaire puisque les contacts doivent être limités afin d'éviter la propagation de la COVID-19.","imageCredits":"Graham Hughes","pressAgencies":[{"id":null,"name":"La Presse canadienne","codeName":"La Presse canadienne"}],"imageCollection":"","concreteImages":[{"mediaLink":{"href":"https://images.radio-canada.ca/v1/ici-info/1x1/montreal-jogging-hiver-saint-laurent.JPG"},"width":2070,"height":2070,"dimensionRatio":"1:1"},{"mediaLink":{"href":"https://images.radio-canada.ca/v1/ici-info/16x9/montreal-jogging-hiver-saint-laurent.JPG"},"width":3000,"height":1688,"dimensionRatio":"16:9"},{"mediaLink":{"href":"https://images.radio-canada.ca/v1/ici-info/17x6/montreal-jogging-hiver-saint-laurent.JPG"},"width":3000,"height":1059,"dimensionRatio":"17:6"},{"mediaLink":{"href":"https://images.radio-canada.ca/v1/ici-info/2x3/montreal-jogging-hiver-saint-laurent.JPG"},"width":1380,"height":2070,"dimensionRatio":"2:3"},{"mediaLink":{"href":"https://images.radio-canada.ca/v1/ici-info/4x3/montreal-jogging-hiver-saint-laurent.JPG"},"width":2760,"height":2070,"dimensionRatio":"4:3"},{"mediaLink":{"href":"https://images.radio-canada.ca/v1/ici-info/perso/montreal-jogging-hiver-saint-laurent.JPG"},"width":3000,"height":2070,"dimensionRatio":"perso"}]},"relatedContents":[{"canonicalWebLink":{"href":"http://ici.radio-canada.ca/nouvelle/1850282/chum-cusm-covid-visite-proche-aidant"},"id":1850282,"type":"Nouvelle","title":"Des hôpitaux montréalais restreignent les visites devant la montée des cas de COVID","summary":"<p>Le CHUM et le CUSM réduisent les visites à la portion congrue depuis dimanche.</p>","summaryImage":null,"publishedLastTimeAt":"2021-12-25T23:14:54.019Z","template":null,"selfLink":{"href":"https://services.radio-canada.ca/neuro/v1/news-stories/1850282"},"summaryMultimediaItem":{"$type":"RC.Neuro.Dtos.v1.ConceptualImage, RC.Neuro.Dtos","contentType":{"id":"19","name":"Image (Picto)"},"alt":"Le centre hospitalier de l'Université de Montréal (CHUM).","legend":"Le centre hospitalier de l'Université de Montréal (CHUM) va suspendre les visites dès dimanche. ","imageCredits":"Ivanoh Demers","pressAgencies":[{"id":null,"name":"Radio-Canada","codeName":"Radio-Canada"}],"imageCollection":"","concreteImages":[{"mediaLink":{"href":"https://images.radio-canada.ca/v1/ici-info/1x1/chum-centre-hospitalier-universite-montreal-85186.jpg"},"width":3173,"height":3173,"dimensionRatio":"1:1"},{"mediaLink":{"href":"https://images.radio-canada.ca/v1/ici-info/16x9/chum-centre-hospitalier-universite-montreal-85186.jpg"},"width":5312,"height":2988,"dimensionRatio":"16:9"},{"mediaLink":{"href":"https://images.radio-canada.ca/v1/ici-info/17x6/chum-centre-hospitalier-universite-montreal-85186.jpg"},"width":5430,"height":1916,"dimensionRatio":"17:6"},{"mediaLink":{"href":"https://images.radio-canada.ca/v1/ici-info/2x3/chum-centre-hospitalier-universite-montreal-85186.jpg"},"width":2413,"height":3620,"dimensionRatio":"2:3"},{"mediaLink":{"href":"https://images.radio-canada.ca/v1/ici-info/4x3/chum-centre-hospitalier-universite-montreal-85186.jpg"},"width":4826,"height":3620,"dimensionRatio":"4:3"},{"mediaLink":{"href":"https://images.radio-canada.ca/v1/ici-info/perso/chum-centre-hospitalier-universite-montreal-85186.jpg"},"width":5430,"height":3620,"dimensionRatio":"perso"}]},"relatedContents":[],"kicker":"","classificationTag":{"id":12,"name":"Nouvelle","codeName":"nouvelle"},"broadcastableItem":null}],"kicker":"","classificationTag":{"id":12,"name":"Nouvelle","codeName":"nouvelle"},"broadcastableItem":null},{"canonicalWebLink":{"href":"http://ici.radio-canada.ca/nouvelle/1850293/mort-desmond-tutu-aparteid-racisme-nobel-paix"},"id":1850293,"type":"Nouvelle","title":"Desmond Tutu, icône de la lutte antiapartheid, s’est éteint à 90&nbsp;ans","summary":"<p>Prix Nobel de la paix en 1984, il se sera accroché jusqu&#x27;au bout à son rêve d&#x27;une Afrique du Sud égalitaire.</p>","summaryImage":{"contentType":{"id":"19","name":"Image (Picto)"},"alt":"Desmond Tutu rit avec une canne à la main.","legend":"Desmond Tutu lors de l'inauguration d'un monument à son honneur au Cap en octobre 2017.","imageCredits":"Mike Hutrchings","pressAgencies":[{"id":null,"name":"Reuters","codeName":"Reuters"}],"imageCollection":"","concreteImages":[{"mediaLink":{"href":"https://images.radio-canada.ca/v1/ici-info/1x1/desmond-tutu-archives-2017-reuters.JPG"},"width":3959,"height":3959,"dimensionRatio":"1:1"},{"mediaLink":{"href":"https://images.radio-canada.ca/v1/ici-info/16x9/desmond-tutu-archives-2017-reuters.JPG"},"width":5817,"height":3272,"dimensionRatio":"16:9"},{"mediaLink":{"href":"https://images.radio-canada.ca/v1/ici-info/17x6/desmond-tutu-archives-2017-reuters.JPG"},"width":5817,"height":2053,"dimensionRatio":"17:6"},{"mediaLink":{"href":"https://images.radio-canada.ca/v1/ici-info/2x3/desmond-tutu-archives-2017-reuters.JPG"},"width":2639,"height":3959,"dimensionRatio":"2:3"},{"mediaLink":{"href":"https://images.radio-canada.ca/v1/ici-info/4x3/desmond-tutu-archives-2017-reuters.JPG"},"width":5279,"height":3959,"dimensionRatio":"4:3"},{"mediaLink":{"href":"https://images.radio-canada.ca/v1/ici-info/perso/desmond-tutu-archives-2017-reuters.JPG"},"width":5817,"height":3959,"dimensionRatio":"perso"}]},"publishedLastTimeAt":"2021-12-26T11:20:38.918Z","template":null,"selfLink":{"href":"https://services.radio-canada.ca/neuro/v1/news-stories/1850293"},"summaryMultimediaItem":{"$type":"RC.Neuro.Dtos.v1.ConceptualImage, RC.Neuro.Dtos","contentType":{"id":"19","name":"Image (Picto)"},"alt":"Une canne à la main, Desmond Tutu rit.","legend":"Desmond Tutu lors de l'inauguration d'un monument en son honneur au Cap en octobre 2017.","imageCredits":"Mike Hutrchings","pressAgencies":[{"id":null,"name":"Reuters","codeName":"Reuters"}],"imageCollection":"","concreteImages":[{"mediaLink":{"href":"https://images.radio-canada.ca/v1/ici-info/1x1/desmond-tutu-archives-2017-reuters.JPG"},"width":3959,"height":3959,"dimensionRatio":"1:1"},{"mediaLink":{"href":"https://images.radio-canada.ca/v1/ici-info/16x9/desmond-tutu-archives-2017-reuters.JPG"},"width":5817,"height":3272,"dimensionRatio":"16:9"},{"mediaLink":{"href":"https://images.radio-canada.ca/v1/ici-info/17x6/desmond-tutu-archives-2017-reuters.JPG"},"width":5817,"height":2053,"dimensionRatio":"17:6"},{"mediaLink":{"href":"https://images.radio-canada.ca/v1/ici-info/2x3/desmond-tutu-archives-2017-reuters.JPG"},"width":2639,"height":3959,"dimensionRatio":"2:3"},{"mediaLink":{"href":"https://images.radio-canada.ca/v1/ici-info/4x3/desmond-tutu-archives-2017-reuters.JPG"},"width":5279,"height":3959,"dimensionRatio":"4:3"},{"mediaLink":{"href":"https://images.radio-canada.ca/v1/ici-info/perso/desmond-tutu-archives-2017-reuters.JPG"},"width":5817,"height":3959,"dimensionRatio":"perso"}]},"relatedContents":[],"kicker":"","classificationTag":{"id":12,"name":"Nouvelle","codeName":"nouvelle"},"broadcastableItem":null},{"canonicalWebLink":{"href":"http://ici.radio-canada.ca/nouvelle/1850301/consommation-jour-apres-noel"},"id":1850301,"type":"Nouvelle","title":"Des soldes d’après Noël en temps de pandémie","summary":"<p>Les commerces doivent limiter leur capacité à 50&nbsp;%. La SAQ et la SQDC ouvriront à partir de 13&nbsp;h. </p>","summaryImage":{"contentType":{"id":"19","name":"Image (Picto)"},"alt":"Un homme passe devant un magasin à Montréal.","legend":"Un homme portant un masque de protection passe devant une vitrine de magasin le lendemain de Noël à Montréal.","imageCredits":"Graham Hughes","pressAgencies":[{"id":null,"name":"La Presse canadienne","codeName":"La Presse canadienne"}],"imageCollection":"","concreteImages":[{"mediaLink":{"href":"https://images.radio-canada.ca/v1/ici-info/1x1/solde-apres-noel-14334.jpg"},"width":1921,"height":1921,"dimensionRatio":"1:1"},{"mediaLink":{"href":"https://images.radio-canada.ca/v1/ici-info/16x9/solde-apres-noel-14334.jpg"},"width":3000,"height":1687,"dimensionRatio":"16:9"},{"mediaLink":{"href":"https://images.radio-canada.ca/v1/ici-info/17x6/solde-apres-noel-14334.jpg"},"width":3000,"height":1059,"dimensionRatio":"17:6"},{"mediaLink":{"href":"https://images.radio-canada.ca/v1/ici-info/2x3/solde-apres-noel-14334.jpg"},"width":1280,"height":1920,"dimensionRatio":"2:3"},{"mediaLink":{"href":"https://images.radio-canada.ca/v1/ici-info/4x3/solde-apres-noel-14334.jpg"},"width":2561,"height":1921,"dimensionRatio":"4:3"},{"mediaLink":{"href":"https://images.radio-canada.ca/v1/ici-info/perso/solde-apres-noel-14334.jpg"},"width":3000,"height":1921,"dimensionRatio":"perso"}]},"publishedLastTimeAt":"2021-12-26T15:09:46.429Z","template":null,"selfLink":{"href":"https://services.radio-canada.ca/neuro/v1/news-stories/1850301"},"summaryMultimediaItem":{"$type":"RC.Neuro.Dtos.v1.ConceptualImage, RC.Neuro.Dtos","contentType":{"id":"19","name":"Image (Picto)"},"alt":"Un homme passe devant un magasin à Montréal.","legend":"Un homme portant un masque de protection passe devant une vitrine de magasin le lendemain de Noël à Montréal (archives).","imageCredits":"Graham Hughes","pressAgencies":[{"id":null,"name":"La Presse canadienne","codeName":"La Presse canadienne"}],"imageCollection":"","concreteImages":[{"mediaLink":{"href":"https://images.radio-canada.ca/v1/ici-info/1x1/solde-apres-noel-14334.jpg"},"width":1921,"height":1921,"dimensionRatio":"1:1"},{"mediaLink":{"href":"https://images.radio-canada.ca/v1/ici-info/16x9/solde-apres-noel-14334.jpg"},"width":3000,"height":1687,"dimensionRatio":"16:9"},{"mediaLink":{"href":"https://images.radio-canada.ca/v1/ici-info/17x6/solde-apres-noel-14334.jpg"},"width":3000,"height":1059,"dimensionRatio":"17:6"},{"mediaLink":{"href":"https://images.radio-canada.ca/v1/ici-info/2x3/solde-apres-noel-14334.jpg"},"width":1280,"height":1920,"dimensionRatio":"2:3"},{"mediaLink":{"href":"https://images.radio-canada.ca/v1/ici-info/4x3/solde-apres-noel-14334.jpg"},"width":2561,"height":1921,"dimensionRatio":"4:3"},{"mediaLink":{"href":"https://images.radio-canada.ca/v1/ici-info/perso/solde-apres-noel-14334.jpg"},"width":3000,"height":1921,"dimensionRatio":"perso"}]},"relatedContents":[],"kicker":"","classificationTag":{"id":12,"name":"Nouvelle","codeName":"nouvelle"},"broadcastableItem":null},{"canonicalWebLink":{"href":"http://ici.radio-canada.ca/nouvelle/1847967/2021-retrospective-premieres-mars-spears-tribunal-benin"},"id":1847967,"type":"Nouvelle","title":"2021, une année de premières","summary":"<p>Il y a des premières pour tout, le grave comme le léger. Voici un tour d’horizon de l’année.</p>","summaryImage":{"contentType":{"id":"19","name":"Image (Picto)"},"alt":"L'hélicoptère Ingenuity en vol.","legend":"L'hélicoptère Ingenuity survole Mars sur une illustration fournie par le Jet Propulsion Laboratory.","imageCredits":"NASA/JPL-Caltech","pressAgencies":[{"id":null,"name":"Reuters","codeName":"Reuters"}],"imageCollection":"","concreteImages":[{"mediaLink":{"href":"https://images.radio-canada.ca/v1/ici-info/1x1/ingenuity-nasa-mars-33206.JPG"},"width":2141,"height":2141,"dimensionRatio":"1:1"},{"mediaLink":{"href":"https://images.radio-canada.ca/v1/ici-info/16x9/ingenuity-nasa-mars-33206.JPG"},"width":3806,"height":2141,"dimensionRatio":"16:9"},{"mediaLink":{"href":"https://images.radio-canada.ca/v1/ici-info/17x6/ingenuity-nasa-mars-33206.JPG"},"width":3820,"height":1348,"dimensionRatio":"17:6"},{"mediaLink":{"href":"https://images.radio-canada.ca/v1/ici-info/2x3/ingenuity-nasa-mars-33206.JPG"},"width":1427,"height":2141,"dimensionRatio":"2:3"},{"mediaLink":{"href":"https://images.radio-canada.ca/v1/ici-info/4x3/ingenuity-nasa-mars-33206.JPG"},"width":2854,"height":2141,"dimensionRatio":"4:3"},{"mediaLink":{"href":"https://images.radio-canada.ca/v1/ici-info/perso/ingenuity-nasa-mars-33206.JPG"},"width":3820,"height":2141,"dimensionRatio":"perso"}]},"publishedLastTimeAt":"2021-12-26T09:00:51.091Z","template":null,"selfLink":{"href":"https://services.radio-canada.ca/neuro/v1/news-stories/1847967"},"summaryMultimediaItem":{"$type":"RC.Neuro.Dtos.v1.ConceptualImage, RC.Neuro.Dtos","contentType":{"id":"19","name":"Image (Picto)"},"alt":"L'hélicoptère Ingenuity en vol.","legend":"L'hélicoptère Ingenuity survole Mars sur une illustration fournie par le Jet Propulsion Laboratory.","imageCredits":"NASA/JPL-Caltech","pressAgencies":[{"id":null,"name":"Reuters","codeName":"Reuters"}],"imageCollection":"","concreteImages":[{"mediaLink":{"href":"https://images.radio-canada.ca/v1/ici-info/1x1/ingenuity-nasa-mars-33206.JPG"},"width":2141,"height":2141,"dimensionRatio":"1:1"},{"mediaLink":{"href":"https://images.radio-canada.ca/v1/ici-info/16x9/ingenuity-nasa-mars-33206.JPG"},"width":3806,"height":2141,"dimensionRatio":"16:9"},{"mediaLink":{"href":"https://images.radio-canada.ca/v1/ici-info/17x6/ingenuity-nasa-mars-33206.JPG"},"width":3820,"height":1348,"dimensionRatio":"17:6"},{"mediaLink":{"href":"https://images.radio-canada.ca/v1/ici-info/2x3/ingenuity-nasa-mars-33206.JPG"},"width":1427,"height":2141,"dimensionRatio":"2:3"},{"mediaLink":{"href":"https://images.radio-canada.ca/v1/ici-info/4x3/ingenuity-nasa-mars-33206.JPG"},"width":2854,"height":2141,"dimensionRatio":"4:3"},{"mediaLink":{"href":"https://images.radio-canada.ca/v1/ici-info/perso/ingenuity-nasa-mars-33206.JPG"},"width":3820,"height":2141,"dimensionRatio":"perso"}]},"relatedContents":[],"kicker":"","classificationTag":{"id":12,"name":"Nouvelle","codeName":"nouvelle"},"broadcastableItem":null},{"canonicalWebLink":{"href":"http://ici.radio-canada.ca/nouvelle/1849141/bureaux-francais-sdf-sans-logement-nantes"},"id":1849141,"type":"Nouvelle","title":"Les<strong> </strong>«&nbsp;Bureaux du Cœur&nbsp;» ouvrent leurs portes aux Français sans logis","summary":"<p>Des entreprises hébergent des personnes à la recherche d&#x27;un logement le soir et les fins de semaine.</p>","summaryImage":{"contentType":{"id":"19","name":"Image (Picto)"},"alt":"Le lit où dort Fortune Obame. ","legend":"Le soir, cette section des bureaux de l'entreprise Nobilito se transforme en chambre où dort Fortune Obame, qui est à la recherche de logement.","imageCredits":"Raphaël Bouvier-Auclair. ","pressAgencies":[{"id":null,"name":"Radio-Canada","codeName":"Radio-Canada"}],"imageCollection":"","concreteImages":[{"mediaLink":{"href":"https://images.radio-canada.ca/v1/ici-info/1x1/obame.JPG"},"width":3024,"height":3024,"dimensionRatio":"1:1"},{"mediaLink":{"href":"https://images.radio-canada.ca/v1/ici-info/16x9/obame.JPG"},"width":4032,"height":2268,"dimensionRatio":"16:9"},{"mediaLink":{"href":"https://images.radio-canada.ca/v1/ici-info/17x6/obame.JPG"},"width":4032,"height":1423,"dimensionRatio":"17:6"},{"mediaLink":{"href":"https://images.radio-canada.ca/v1/ici-info/2x3/obame.JPG"},"width":2016,"height":3024,"dimensionRatio":"2:3"},{"mediaLink":{"href":"https://images.radio-canada.ca/v1/ici-info/4x3/obame.JPG"},"width":4032,"height":3024,"dimensionRatio":"4:3"},{"mediaLink":{"href":"https://images.radio-canada.ca/v1/ici-info/perso/obame.JPG"},"width":4032,"height":3024,"dimensionRatio":"perso"}]},"publishedLastTimeAt":"2021-12-26T09:01:08.586Z","template":null,"selfLink":{"href":"https://services.radio-canada.ca/neuro/v1/news-stories/1849141"},"summaryMultimediaItem":{"$type":"RC.Neuro.Dtos.v1.ConceptualImage, RC.Neuro.Dtos","contentType":{"id":"19","name":"Image (Picto)"},"alt":"Le lit où dort Fortune Obame. ","legend":"Le soir, cette section des bureaux de l'entreprise Nobilito se transforme en chambre où dort Fortune Obame, qui est à la recherche d'un logement.","imageCredits":"Raphaël Bouvier-Auclair. ","pressAgencies":[{"id":null,"name":"Radio-Canada","codeName":"Radio-Canada"}],"imageCollection":"","concreteImages":[{"mediaLink":{"href":"https://images.radio-canada.ca/v1/ici-info/1x1/obame.JPG"},"width":3024,"height":3024,"dimensionRatio":"1:1"},{"mediaLink":{"href":"https://images.radio-canada.ca/v1/ici-info/16x9/obame.JPG"},"width":4032,"height":2268,"dimensionRatio":"16:9"},{"mediaLink":{"href":"https://images.radio-canada.ca/v1/ici-info/17x6/obame.JPG"},"width":4032,"height":1423,"dimensionRatio":"17:6"},{"mediaLink":{"href":"https://images.radio-canada.ca/v1/ici-info/2x3/obame.JPG"},"width":2016,"height":3024,"dimensionRatio":"2:3"},{"mediaLink":{"href":"https://images.radio-canada.ca/v1/ici-info/4x3/obame.JPG"},"width":4032,"height":3024,"dimensionRatio":"4:3"},{"mediaLink":{"href":"https://images.radio-canada.ca/v1/ici-info/perso/obame.JPG"},"width":4032,"height":3024,"dimensionRatio":"perso"}]},"relatedContents":[],"kicker":"","classificationTag":{"id":12,"name":"Nouvelle","codeName":"nouvelle"},"broadcastableItem":null},{"canonicalWebLink":{"href":"http://ici.radio-canada.ca/nouvelle/1847062/politique-ontario-doug-ford-mulroney-queens-park"},"id":1847062,"type":"Nouvelle","title":"Sept&nbsp;citations qui ont marqué la politique cette année en Ontario","summary":"<p> Retour sur quelques citations marquantes tirées de la scène politique en&nbsp;2021.</p>","summaryImage":{"contentType":{"id":"19","name":"Image (Picto)"},"alt":"Sanaa-Marie Best, deux ans, pleure alors que le premier ministre de l'Ontario, Doug Ford, pose pour une photo lors d'une visite du centre de services de santé communautaire de Wellfort à Mississauga.","legend":"Une séance photo entre le premier ministre de l'Ontario et une fillette n'a pas eu les résultats escomptés le 9 février 2021, lors d'une visite officielle d'un centre de vaccination à Mississauga.","imageCredits":"Nathan Denette","pressAgencies":[{"id":null,"name":"La Presse canadienne","codeName":"La Presse canadienne"}],"imageCollection":"","concreteImages":[{"mediaLink":{"href":"https://images.radio-canada.ca/v1/ici-info/1x1/doug-ford-covid-enfant.jpg"},"width":2993,"height":2993,"dimensionRatio":"1:1"},{"mediaLink":{"href":"https://images.radio-canada.ca/v1/ici-info/16x9/doug-ford-covid-enfant.jpg"},"width":4200,"height":2363,"dimensionRatio":"16:9"},{"mediaLink":{"href":"https://images.radio-canada.ca/v1/ici-info/17x6/doug-ford-covid-enfant.jpg"},"width":4200,"height":1482,"dimensionRatio":"17:6"},{"mediaLink":{"href":"https://images.radio-canada.ca/v1/ici-info/2x3/doug-ford-covid-enfant.jpg"},"width":1995,"height":2993,"dimensionRatio":"2:3"},{"mediaLink":{"href":"https://images.radio-canada.ca/v1/ici-info/4x3/doug-ford-covid-enfant.jpg"},"width":3991,"height":2993,"dimensionRatio":"4:3"},{"mediaLink":{"href":"https://images.radio-canada.ca/v1/ici-info/perso/doug-ford-covid-enfant.jpg"},"width":4200,"height":2993,"dimensionRatio":"perso"}]},"publishedLastTimeAt":"2021-12-26T11:30:08.935Z","template":null,"selfLink":{"href":"https://services.radio-canada.ca/neuro/v1/news-stories/1847062"},"summaryMultimediaItem":{"$type":"RC.Neuro.Dtos.v1.ConceptualImage, RC.Neuro.Dtos","contentType":{"id":"19","name":"Image (Picto)"},"alt":"Sanaa-Marie Best, deux ans, pleure alors que le premier ministre de l'Ontario, Doug Ford, pose pour une photo lors d'une visite du centre de services de santé communautaire de Wellfort à Mississauga.","legend":"Une séance photo entre le premier ministre de l'Ontario et une fillette n'a pas eu les résultats escomptés le 9 février 2021, lors d'une visite officielle d'un centre de vaccination à Mississauga.","imageCredits":"Nathan Denette","pressAgencies":[{"id":null,"name":"La Presse canadienne","codeName":"La Presse canadienne"}],"imageCollection":"","concreteImages":[{"mediaLink":{"href":"https://images.radio-canada.ca/v1/ici-info/1x1/doug-ford-covid-enfant.jpg"},"width":2993,"height":2993,"dimensionRatio":"1:1"},{"mediaLink":{"href":"https://images.radio-canada.ca/v1/ici-info/16x9/doug-ford-covid-enfant.jpg"},"width":4200,"height":2363,"dimensionRatio":"16:9"},{"mediaLink":{"href":"https://images.radio-canada.ca/v1/ici-info/17x6/doug-ford-covid-enfant.jpg"},"width":4200,"height":1482,"dimensionRatio":"17:6"},{"mediaLink":{"href":"https://images.radio-canada.ca/v1/ici-info/2x3/doug-ford-covid-enfant.jpg"},"width":1995,"height":2993,"dimensionRatio":"2:3"},{"mediaLink":{"href":"https://images.radio-canada.ca/v1/ici-info/4x3/doug-ford-covid-enfant.jpg"},"width":3991,"height":2993,"dimensionRatio":"4:3"},{"mediaLink":{"href":"https://images.radio-canada.ca/v1/ici-info/perso/doug-ford-covid-enfant.jpg"},"width":4200,"height":2993,"dimensionRatio":"perso"}]},"relatedContents":[],"kicker":"","classificationTag":{"id":12,"name":"Nouvelle","codeName":"nouvelle"},"broadcastableItem":null},{"canonicalWebLink":{"href":"http://ici.radio-canada.ca/nouvelle/1850295/nouveau-responsable-xinjiang-minorite-ouighour"},"id":1850295,"type":"Nouvelle","title":"La Chine nomme un nouveau responsable pour diriger le Xinjiang","summary":"<p>L&#x27;ancien responsable est sur la liste noire américaine pour son implication dans la répression des Ouïghours.</p>","summaryImage":{"contentType":{"id":"19","name":"Image (Picto)"},"alt":"Ma Xingrui prend la parole.","legend":"Le Xinjiang a désormais à sa tête Ma Xingrui, qui dirigeait jusque-là la province du Guangdong (sud) dont Canton est la capitale (archives).","imageCredits":"PHILIP FONG","pressAgencies":[{"id":null,"name":"Getty Images","codeName":"Getty Images"}],"imageCollection":"","concreteImages":[{"mediaLink":{"href":"https://images.radio-canada.ca/v1/ici-info/1x1/ma-xingrui.jpg"},"width":2667,"height":2667,"dimensionRatio":"1:1"},{"mediaLink":{"href":"https://images.radio-canada.ca/v1/ici-info/16x9/ma-xingrui.jpg"},"width":4000,"height":2250,"dimensionRatio":"16:9"},{"mediaLink":{"href":"https://images.radio-canada.ca/v1/ici-info/17x6/ma-xingrui.jpg"},"width":4000,"height":1412,"dimensionRatio":"17:6"},{"mediaLink":{"href":"https://images.radio-canada.ca/v1/ici-info/2x3/ma-xingrui.jpg"},"width":1778,"height":2667,"dimensionRatio":"2:3"},{"mediaLink":{"href":"https://images.radio-canada.ca/v1/ici-info/4x3/ma-xingrui.jpg"},"width":3556,"height":2667,"dimensionRatio":"4:3"},{"mediaLink":{"href":"https://images.radio-canada.ca/v1/ici-info/perso/ma-xingrui.jpg"},"width":4000,"height":2667,"dimensionRatio":"perso"}]},"publishedLastTimeAt":"2021-12-26T12:09:39.330Z","template":null,"selfLink":{"href":"https://services.radio-canada.ca/neuro/v1/news-stories/1850295"},"summaryMultimediaItem":{"$type":"RC.Neuro.Dtos.v1.ConceptualImage, RC.Neuro.Dtos","contentType":{"id":"19","name":"Image (Picto)"},"alt":"Ma Xingrui prend la parole.","legend":"Le Xinjiang a désormais à sa tête Ma Xingrui, qui dirigeait jusque-là la province du Guangdong (sud), dont Canton est la capitale.","imageCredits":"PHILIP FONG","pressAgencies":[{"id":null,"name":"Getty Images","codeName":"Getty Images"}],"imageCollection":"","concreteImages":[{"mediaLink":{"href":"https://images.radio-canada.ca/v1/ici-info/1x1/ma-xingrui.jpg"},"width":2667,"height":2667,"dimensionRatio":"1:1"},{"mediaLink":{"href":"https://images.radio-canada.ca/v1/ici-info/16x9/ma-xingrui.jpg"},"width":4000,"height":2250,"dimensionRatio":"16:9"},{"mediaLink":{"href":"https://images.radio-canada.ca/v1/ici-info/17x6/ma-xingrui.jpg"},"width":4000,"height":1412,"dimensionRatio":"17:6"},{"mediaLink":{"href":"https://images.radio-canada.ca/v1/ici-info/2x3/ma-xingrui.jpg"},"width":1778,"height":2667,"dimensionRatio":"2:3"},{"mediaLink":{"href":"https://images.radio-canada.ca/v1/ici-info/4x3/ma-xingrui.jpg"},"width":3556,"height":2667,"dimensionRatio":"4:3"},{"mediaLink":{"href":"https://images.radio-canada.ca/v1/ici-info/perso/ma-xingrui.jpg"},"width":4000,"height":2667,"dimensionRatio":"perso"}]},"relatedContents":[],"kicker":"","classificationTag":{"id":12,"name":"Nouvelle","codeName":"nouvelle"},"broadcastableItem":null},{"canonicalWebLink":{"href":"http://ici.radio-canada.ca/nouvelle/1850261/mauricie-a40-accident-route"},"id":1850261,"type":"Nouvelle","title":"Un carambolage sur l’A-40 à Yamachiche fait une dizaine de blessés","summary":"<p>Après qu&#x27;un tronçon eut été bloqué pendant quelques heures, l&#x27;autoroute 40 a pu rouvrir en direction est.</p>","summaryImage":{"contentType":{"id":"19","name":"Image (Picto)"},"alt":"Une personne observe des voitures accidentées.","legend":"Quelque 70 véhicules auraient été impliqués dans le carambolage.","imageCredits":"Élise Gagnon","pressAgencies":[],"imageCollection":"","concreteImages":[{"mediaLink":{"href":"https://images.radio-canada.ca/v1/ici-info/1x1/accident-yamachiche-a40-02.JPG"},"width":3024,"height":3024,"dimensionRatio":"1:1"},{"mediaLink":{"href":"https://images.radio-canada.ca/v1/ici-info/16x9/accident-yamachiche-a40-02.JPG"},"width":4032,"height":2268,"dimensionRatio":"16:9"},{"mediaLink":{"href":"https://images.radio-canada.ca/v1/ici-info/17x6/accident-yamachiche-a40-02.JPG"},"width":4032,"height":1423,"dimensionRatio":"17:6"},{"mediaLink":{"href":"https://images.radio-canada.ca/v1/ici-info/2x3/accident-yamachiche-a40-02.JPG"},"width":2016,"height":3024,"dimensionRatio":"2:3"},{"mediaLink":{"href":"https://images.radio-canada.ca/v1/ici-info/4x3/accident-yamachiche-a40-02.JPG"},"width":4032,"height":3024,"dimensionRatio":"4:3"},{"mediaLink":{"href":"https://images.radio-canada.ca/v1/ici-info/perso/accident-yamachiche-a40-02.JPG"},"width":4032,"height":3024,"dimensionRatio":"perso"}]},"publishedLastTimeAt":"2021-12-26T13:15:20.646Z","template":null,"selfLink":{"href":"https://services.radio-canada.ca/neuro/v1/news-stories/1850261"},"summaryMultimediaItem":{"$type":"RC.Neuro.Dtos.v1.ConceptualImage, RC.Neuro.Dtos","contentType":{"id":"19","name":"Image (Picto)"},"alt":"Une personne observe des voitures accidentées.","legend":"Environ 70 véhicules auraient été impliqués dans le carambolage.","imageCredits":"Élise Gagnon","pressAgencies":[],"imageCollection":"","concreteImages":[{"mediaLink":{"href":"https://images.radio-canada.ca/v1/ici-info/1x1/accident-yamachiche-a40-02.JPG"},"width":3024,"height":3024,"dimensionRatio":"1:1"},{"mediaLink":{"href":"https://images.radio-canada.ca/v1/ici-info/16x9/accident-yamachiche-a40-02.JPG"},"width":4032,"height":2268,"dimensionRatio":"16:9"},{"mediaLink":{"href":"https://images.radio-canada.ca/v1/ici-info/17x6/accident-yamachiche-a40-02.JPG"},"width":4032,"height":1423,"dimensionRatio":"17:6"},{"mediaLink":{"href":"https://images.radio-canada.ca/v1/ici-info/2x3/accident-yamachiche-a40-02.JPG"},"width":2016,"height":3024,"dimensionRatio":"2:3"},{"mediaLink":{"href":"https://images.radio-canada.ca/v1/ici-info/4x3/accident-yamachiche-a40-02.JPG"},"width":4032,"height":3024,"dimensionRatio":"4:3"},{"mediaLink":{"href":"https://images.radio-canada.ca/v1/ici-info/perso/accident-yamachiche-a40-02.JPG"},"width":4032,"height":3024,"dimensionRatio":"perso"}]},"relatedContents":[],"kicker":"","classificationTag":{"id":12,"name":"Nouvelle","codeName":"nouvelle"},"broadcastableItem":null},{"canonicalWebLink":{"href":"http://ici.radio-canada.ca/nouvelle/1850292/coronavirus-omicron-record-infections"},"id":1850292,"type":"Nouvelle","title":"L’Ontario signale plus de 10&nbsp;000&nbsp;cas de COVID-19 pour la première fois","summary":"<p>Le nombre réel de cas est probablement plus élevé, selon des experts.</p>","summaryImage":{"contentType":{"id":"19","name":"Image (Picto)"},"alt":"Une femme masquée dans un métro de Toronto.","legend":"Plus de 82,4 % des Ontariens éligibles ont reçu leurs deux doses des vaccins contre la COVID-19.","imageCredits":"","pressAgencies":[{"id":null,"name":"CBC/Evan Mitsui","codeName":"CBC/Evan Mitsui"}],"imageCollection":"","concreteImages":[{"mediaLink":{"href":"https://images.radio-canada.ca/v1/ici-regions/1x1/covid-19-ontario-metro-toronto-masque-passager.png"},"width":903,"height":903,"dimensionRatio":"1:1"},{"mediaLink":{"href":"https://images.radio-canada.ca/v1/ici-regions/16x9/covid-19-ontario-metro-toronto-masque-passager.png"},"width":1354,"height":762,"dimensionRatio":"16:9"},{"mediaLink":{"href":"https://images.radio-canada.ca/v1/ici-regions/17x6/covid-19-ontario-metro-toronto-masque-passager.png"},"width":1354,"height":478,"dimensionRatio":"17:6"},{"mediaLink":{"href":"https://images.radio-canada.ca/v1/ici-regions/2x3/covid-19-ontario-metro-toronto-masque-passager.png"},"width":602,"height":903,"dimensionRatio":"2:3"},{"mediaLink":{"href":"https://images.radio-canada.ca/v1/ici-regions/4x3/covid-19-ontario-metro-toronto-masque-passager.png"},"width":1204,"height":903,"dimensionRatio":"4:3"},{"mediaLink":{"href":"https://images.radio-canada.ca/v1/ici-regions/perso/covid-19-ontario-metro-toronto-masque-passager.png"},"width":1354,"height":903,"dimensionRatio":"perso"}]},"publishedLastTimeAt":"2021-12-26T03:51:01.475Z","template":null,"selfLink":{"href":"https://services.radio-canada.ca/neuro/v1/news-stories/1850292"},"summaryMultimediaItem":{"$type":"RC.Neuro.Dtos.v1.ConceptualImage, RC.Neuro.Dtos","contentType":{"id":"19","name":"Image (Picto)"},"alt":"Une femme masquée dans un métro de Toronto.","legend":"Des experts ont expliqué que le nombre réel de cas est probablement beaucoup plus élevé que ceux signalés chaque jour, car de nombreux bureaux de santé publique ont atteint leur capacité maximale de test.","imageCredits":"","pressAgencies":[{"id":null,"name":"CBC/Evan Mitsui","codeName":"CBC/Evan Mitsui"}],"imageCollection":"","concreteImages":[{"mediaLink":{"href":"https://images.radio-canada.ca/v1/ici-regions/1x1/covid-19-ontario-metro-toronto-masque-passager.png"},"width":903,"height":903,"dimensionRatio":"1:1"},{"mediaLink":{"href":"https://images.radio-canada.ca/v1/ici-regions/16x9/covid-19-ontario-metro-toronto-masque-passager.png"},"width":1354,"height":762,"dimensionRatio":"16:9"},{"mediaLink":{"href":"https://images.radio-canada.ca/v1/ici-regions/17x6/covid-19-ontario-metro-toronto-masque-passager.png"},"width":1354,"height":478,"dimensionRatio":"17:6"},{"mediaLink":{"href":"https://images.radio-canada.ca/v1/ici-regions/2x3/covid-19-ontario-metro-toronto-masque-passager.png"},"width":602,"height":903,"dimensionRatio":"2:3"},{"mediaLink":{"href":"https://images.radio-canada.ca/v1/ici-regions/4x3/covid-19-ontario-metro-toronto-masque-passager.png"},"width":1204,"height":903,"dimensionRatio":"4:3"},{"mediaLink":{"href":"https://images.radio-canada.ca/v1/ici-regions/perso/covid-19-ontario-metro-toronto-masque-passager.png"},"width":1354,"height":903,"dimensionRatio":"perso"}]},"relatedContents":[],"kicker":"","classificationTag":{"id":12,"name":"Nouvelle","codeName":"nouvelle"},"broadcastableItem":null}]}}