{"id":1005685,"selfLink":{"href":"https://services.radio-canada.ca/neuro/v1/topics/1005685"},"canonicalWebLink":{"href":"http://ici.radio-canada.ca/dossier/1005685/epidemie-coronavirus-covid-19-monde"},"previousCanonicalWebLinks":[],"lineupLink":{"href":"https://services.radio-canada.ca/neuro/v1/topics/1005685/lineup?pageNumber=1"},"title":"COVID-19 : tout sur la pandémie","name":"Coronavirus","summary":"<p>Apparu en Chine fin 2019, le coronavirus s'est depuis propagé sur tous les continents. État de la situation.</p>","summaryMultimediaContent":{"$type":"RC.Neuro.Dtos.v1.ConceptualImage, RC.Neuro.Dtos","contentType":{"id":"19","name":"Image (Picto)"},"alt":"Une représentation artistique de la Terre et du coronavirus.","legend":"Apparu en Chine fin 2019, le coronavirus s'est depuis propagé sur tous les continents. État de la situation.","imageCredits":"","pressAgencies":[{"id":null,"name":"Centers for Disease Control and Prevention","codeName":"Centers for Disease Control and Prevention"}],"imageCollection":"","concreteImages":[{"mediaLink":{"href":"https://images.radio-canada.ca/v1/ici-info/1x1/dossier-coronavirus-monde.jpg"},"width":1080,"height":1080,"dimensionRatio":"1:1"},{"mediaLink":{"href":"https://images.radio-canada.ca/v1/ici-info/16x9/dossier-coronavirus-monde.jpg"},"width":1920,"height":1080,"dimensionRatio":"16:9"},{"mediaLink":{"href":"https://images.radio-canada.ca/v1/ici-info/17x6/dossier-coronavirus-monde.jpg"},"width":1920,"height":678,"dimensionRatio":"17:6"},{"mediaLink":{"href":"https://images.radio-canada.ca/v1/ici-info/2x3/dossier-coronavirus-monde.jpg"},"width":720,"height":1080,"dimensionRatio":"2:3"},{"mediaLink":{"href":"https://images.radio-canada.ca/v1/ici-info/4x3/dossier-coronavirus-monde.jpg"},"width":1440,"height":1080,"dimensionRatio":"4:3"},{"mediaLink":{"href":"https://images.radio-canada.ca/v1/ici-info/perso/dossier-coronavirus-monde.jpg"},"width":1920,"height":1080,"dimensionRatio":"perso"}]},"publishedFirstTimeAt":"2020-03-10T14:54:04.121Z","publishedLastTimeAt":"2021-10-16T17:05:41.689Z","template":null,"body":{"html":"<p>1793790</p>\n\n\n<p>1781411</p>\n<p>1763649</p>\n\n<p>1743457</p>\n<p>1732561Que faire si je pense être atteint du coronavirus?</p>","attachments":[]},"summaryMultimediaContentForDetail":{"$type":"RC.Neuro.Dtos.v1.ConceptualImage, RC.Neuro.Dtos","contentType":{"id":"19","name":"Image (Picto)"},"alt":"Une représentation artistique de la Terre et du coronavirus.","legend":"Apparu en Chine fin 2019, le coronavirus s'est depuis propagé sur tous les continents. État de la situation.","imageCredits":"","pressAgencies":[{"id":null,"name":"Centers for Disease Control and Prevention","codeName":"Centers for Disease Control and Prevention"}],"imageCollection":"","concreteImages":[{"mediaLink":{"href":"https://images.radio-canada.ca/v1/ici-info/1x1/dossier-coronavirus-monde.jpg"},"width":1080,"height":1080,"dimensionRatio":"1:1"},{"mediaLink":{"href":"https://images.radio-canada.ca/v1/ici-info/16x9/dossier-coronavirus-monde.jpg"},"width":1920,"height":1080,"dimensionRatio":"16:9"},{"mediaLink":{"href":"https://images.radio-canada.ca/v1/ici-info/17x6/dossier-coronavirus-monde.jpg"},"width":1920,"height":678,"dimensionRatio":"17:6"},{"mediaLink":{"href":"https://images.radio-canada.ca/v1/ici-info/2x3/dossier-coronavirus-monde.jpg"},"width":720,"height":1080,"dimensionRatio":"2:3"},{"mediaLink":{"href":"https://images.radio-canada.ca/v1/ici-info/4x3/dossier-coronavirus-monde.jpg"},"width":1440,"height":1080,"dimensionRatio":"4:3"},{"mediaLink":{"href":"https://images.radio-canada.ca/v1/ici-info/perso/dossier-coronavirus-monde.jpg"},"width":1920,"height":1080,"dimensionRatio":"perso"}]},"subSector":{"id":"1","name":"Info National","region":null},"themeTag":{"id":"8","name":"Santé"},"subThemeTags":[],"regionTags":[],"isOfRegionalInterestOnly":false,"customTags":[],"signaturesV2":[],"shareableTitle":"COVID-19 : tout sur la pandémie","shareableSummary":"<p>Apparu en Chine fin 2019, le coronavirus s'est depuis propagé sur tous les continents. État de la situation.</p>","shareableSummaryMultimediaContent":null,"items":[{"referredContent":{"$type":"RC.Neuro.Dtos.v1.NewsStorySummary, RC.Neuro.Dtos","contentType":{"id":"11","name":"Nouvelle"},"id":"1832704","globalId":"11-1832704","canonicalWebLink":{"href":"http://ici.radio-canada.ca/nouvelle/1832704/act-oms-merck-molnupiravir-vaccin"},"kicker":"","outOfContextTitle":"Un programme de l’OMS se fixe pour objectif la fourniture d'un traitement antiviral à 10 $ par posologie pour les patients atteints de la COVID-19","title":"Un programme de l’OMS veut acheter un traitement anti-COVID à 10 $","summary":"<p>La pilule molnupiravir du groupe pharmaceutique américain Merck sera probablement l&#x27;un de ces médicaments.</p>","summaryMultimediaItem":{"$type":"RC.Neuro.Dtos.v1.ConceptualImage, RC.Neuro.Dtos","contentType":{"id":"19","name":"Image (Picto)"},"alt":"Le siège social de l'Organisation mondiale de la santé à Genève en Suisse.","legend":"Le siège social de l'Organisation mondiale de la santé à Genève, en Suisse.","imageCredits":"Denis Balibouse","pressAgencies":[{"id":null,"name":"Reuters","codeName":"Reuters"}],"imageCollection":"","concreteImages":[{"mediaLink":{"href":"https://images.radio-canada.ca/v1/ici-info/1x1/oms-geneve.JPG"},"width":3133,"height":3133,"dimensionRatio":"1:1"},{"mediaLink":{"href":"https://images.radio-canada.ca/v1/ici-info/16x9/oms-geneve.JPG"},"width":4646,"height":2613,"dimensionRatio":"16:9"},{"mediaLink":{"href":"https://images.radio-canada.ca/v1/ici-info/17x6/oms-geneve.JPG"},"width":4646,"height":1640,"dimensionRatio":"17:6"},{"mediaLink":{"href":"https://images.radio-canada.ca/v1/ici-info/2x3/oms-geneve.JPG"},"width":2089,"height":3133,"dimensionRatio":"2:3"},{"mediaLink":{"href":"https://images.radio-canada.ca/v1/ici-info/4x3/oms-geneve.JPG"},"width":4177,"height":3133,"dimensionRatio":"4:3"},{"mediaLink":{"href":"https://images.radio-canada.ca/v1/ici-info/perso/oms-geneve.JPG"},"width":4646,"height":3133,"dimensionRatio":"perso"}]},"themeTag":{"id":"8","name":"Santé"},"subThemeTags":[{"id":"518","name":"Coronavirus"},{"id":"208","name":"Recherche médicale"}],"publishedLastTimeAt":"2021-10-19T10:28:01.654Z","canonicalWebLinkOverride":null,"primaryClassificationTag":{"id":"12","name":"Nouvelle","codeName":"nouvelle"}},"itemTemplate":{"id":1,"name":"Carte régulière"}},{"referredContent":{"$type":"RC.Neuro.Dtos.v1.NewsStorySummary, RC.Neuro.Dtos","contentType":{"id":"11","name":"Nouvelle"},"id":"1832638","globalId":"11-1832638","canonicalWebLink":{"href":"http://ici.radio-canada.ca/nouvelle/1832638/covid-enfants-pfizer-doses-innocuite"},"kicker":"","outOfContextTitle":"Pfizer demande à Santé Canada d'approuver le premier vaccin contre la COVID-19 pour les enfants âgés de 5 à 11 ans","title":"Pfizer soumet un vaccin pour les 5-11&nbsp;ans à Santé Canada","summary":"<p>Le vaccin de Pfizer-BioNTech a également été testé sur des enfants dès l&#x27;âge de six&nbsp;mois.</p>","summaryMultimediaItem":{"$type":"RC.Neuro.Dtos.v1.ConceptualImage, RC.Neuro.Dtos","contentType":{"id":"19","name":"Image (Picto)"},"alt":"Une personne applique un petit coton à l'endroit de la piqûre du vaccin.","legend":"C'est la première demande que Santé Canada reçoit pour l'utilisation d'un vaccin pour les 5-11 ans.","imageCredits":"","pressAgencies":[{"id":null,"name":"iStock","codeName":"iStock"}],"imageCollection":"","concreteImages":[{"mediaLink":{"href":"https://images.radio-canada.ca/v1/ici-info/1x1/vaccin-jeunes-adolescents-manitoba-67281.jpg"},"width":1414,"height":1414,"dimensionRatio":"1:1"},{"mediaLink":{"href":"https://images.radio-canada.ca/v1/ici-info/16x9/vaccin-jeunes-adolescents-manitoba-67281.jpg"},"width":2121,"height":1193,"dimensionRatio":"16:9"},{"mediaLink":{"href":"https://images.radio-canada.ca/v1/ici-info/17x6/vaccin-jeunes-adolescents-manitoba-67281.jpg"},"width":2121,"height":749,"dimensionRatio":"17:6"},{"mediaLink":{"href":"https://images.radio-canada.ca/v1/ici-info/2x3/vaccin-jeunes-adolescents-manitoba-67281.jpg"},"width":942,"height":1413,"dimensionRatio":"2:3"},{"mediaLink":{"href":"https://images.radio-canada.ca/v1/ici-info/4x3/vaccin-jeunes-adolescents-manitoba-67281.jpg"},"width":1885,"height":1414,"dimensionRatio":"4:3"},{"mediaLink":{"href":"https://images.radio-canada.ca/v1/ici-info/perso/vaccin-jeunes-adolescents-manitoba-67281.jpg"},"width":2121,"height":1414,"dimensionRatio":"perso"}]},"themeTag":{"id":"8","name":"Santé"},"subThemeTags":[{"id":"80","name":"Santé publique"}],"publishedLastTimeAt":"2021-10-18T22:53:51.757Z","canonicalWebLinkOverride":null,"primaryClassificationTag":{"id":"12","name":"Nouvelle","codeName":"nouvelle"}},"itemTemplate":{"id":1,"name":"Carte régulière"}},{"referredContent":{"$type":"RC.Neuro.Dtos.v1.NewsStorySummary, RC.Neuro.Dtos","contentType":{"id":"11","name":"Nouvelle"},"id":"1832526","globalId":"11-1832526","canonicalWebLink":{"href":"http://ici.radio-canada.ca/nouvelle/1832526/coronavirus-passeport-vaccinal-provinces-canada-etats-americains"},"kicker":"","outOfContextTitle":"Le gouvernement du Québec lance une nouvelle preuve de vaccination destinée aux voyageurs qui sortent de la province","title":"Une nouvelle preuve de vaccination offerte aux voyageurs québécois","summary":"<p>Cette preuve pourra être utilisée à l&#x27;extérieur du Québec.</p>","summaryMultimediaItem":{"$type":"RC.Neuro.Dtos.v1.ConceptualImage, RC.Neuro.Dtos","contentType":{"id":"19","name":"Image (Picto)"},"alt":"Un serveur derrière le bar regarde le téléphone que lui montre le client assis devant lui.","legend":"Un client montre sa preuve de vaccination contre la COVID-19 à un employé du Clinton Hall, une brasserie de Manhattan, aux États-Unis, le 17 août 2021.","imageCredits":"Andrew Kelly","pressAgencies":[{"id":null,"name":"Reuters","codeName":"Reuters"}],"imageCollection":"","concreteImages":[{"mediaLink":{"href":"https://images.radio-canada.ca/v1/ici-info/1x1/preuve-vaccination-covid-restaurant-covid-19-bar-passeport-vaccinal.JPG"},"width":3791,"height":3791,"dimensionRatio":"1:1"},{"mediaLink":{"href":"https://images.radio-canada.ca/v1/ici-info/16x9/preuve-vaccination-covid-restaurant-covid-19-bar-passeport-vaccinal.JPG"},"width":4466,"height":2512,"dimensionRatio":"16:9"},{"mediaLink":{"href":"https://images.radio-canada.ca/v1/ici-info/17x6/preuve-vaccination-covid-restaurant-covid-19-bar-passeport-vaccinal.JPG"},"width":5688,"height":2008,"dimensionRatio":"17:6"},{"mediaLink":{"href":"https://images.radio-canada.ca/v1/ici-info/2x3/preuve-vaccination-covid-restaurant-covid-19-bar-passeport-vaccinal.JPG"},"width":2527,"height":3791,"dimensionRatio":"2:3"},{"mediaLink":{"href":"https://images.radio-canada.ca/v1/ici-info/4x3/preuve-vaccination-covid-restaurant-covid-19-bar-passeport-vaccinal.JPG"},"width":4067,"height":3050,"dimensionRatio":"4:3"},{"mediaLink":{"href":"https://images.radio-canada.ca/v1/ici-info/perso/preuve-vaccination-covid-restaurant-covid-19-bar-passeport-vaccinal.JPG"},"width":5688,"height":3791,"dimensionRatio":"perso"}]},"themeTag":{"id":"13","name":"Politique"},"subThemeTags":[{"id":"102","name":"Politique provinciale"},{"id":"518","name":"Coronavirus"},{"id":"83","name":"Tourisme"},{"id":"80","name":"Santé publique"},{"id":"232","name":"Vaccination"}],"publishedLastTimeAt":"2021-10-18T23:30:40.022Z","canonicalWebLinkOverride":null,"primaryClassificationTag":{"id":"12","name":"Nouvelle","codeName":"nouvelle"}},"itemTemplate":{"id":1,"name":"Carte régulière"}},{"referredContent":{"$type":"RC.Neuro.Dtos.v1.NewsStorySummary, RC.Neuro.Dtos","contentType":{"id":"11","name":"Nouvelle"},"id":"1832680","globalId":"11-1832680","canonicalWebLink":{"href":"http://ici.radio-canada.ca/nouvelle/1832680/prison-talbot-centre-detention-sherbrooke-eclosion-covid-octobre-2021"},"kicker":"","outOfContextTitle":"L'éclosion de COVID-19 à l'Établissement de détention de Sherbrooke prend de l'ampleur, avec 33 cas positifs","title":"33&nbsp;personnes atteintes de la COVID à l’Établissement de détention de Sherbrooke","summary":"<p>L&#x27;éclosion de COVID-19&nbsp;à l&#x27;Établissement de détention de Sherbrooke prend de l&#x27;ampleur.</p>","summaryMultimediaItem":{"$type":"RC.Neuro.Dtos.v1.ConceptualImage, RC.Neuro.Dtos","contentType":{"id":"19","name":"Image (Picto)"},"alt":"L'affiche de l'établissement de détention de la prison Talbot, à Sherbrooke.","legend":"L'éclosion de COVID-19 à l'Établissement de détention de Sherbrooke prend de l'ampleur. (archives)","imageCredits":"","pressAgencies":[{"id":null,"name":"Radio-Canada","codeName":"Radio-Canada"}],"imageCollection":"","concreteImages":[{"mediaLink":{"href":"https://images.radio-canada.ca/v1/ici-info/1x1/prison-talbot-sherbrooke.jpg"},"width":1079,"height":1080,"dimensionRatio":"1:1"},{"mediaLink":{"href":"https://images.radio-canada.ca/v1/ici-info/16x9/prison-talbot-sherbrooke.jpg"},"width":1919,"height":1079,"dimensionRatio":"16:9"},{"mediaLink":{"href":"https://images.radio-canada.ca/v1/ici-info/17x6/prison-talbot-sherbrooke.jpg"},"width":1919,"height":678,"dimensionRatio":"17:6"},{"mediaLink":{"href":"https://images.radio-canada.ca/v1/ici-info/2x3/prison-talbot-sherbrooke.jpg"},"width":719,"height":1080,"dimensionRatio":"2:3"},{"mediaLink":{"href":"https://images.radio-canada.ca/v1/ici-info/4x3/prison-talbot-sherbrooke.jpg"},"width":1439,"height":1079,"dimensionRatio":"4:3"},{"mediaLink":{"href":"https://images.radio-canada.ca/v1/ici-info/perso/prison-talbot-sherbrooke.jpg"},"width":1919,"height":1080,"dimensionRatio":"perso"}]},"themeTag":{"id":"8","name":"Santé"},"subThemeTags":[{"id":"518","name":"Coronavirus"}],"publishedLastTimeAt":"2021-10-19T01:14:11.435Z","canonicalWebLinkOverride":null,"primaryClassificationTag":{"id":"12","name":"Nouvelle","codeName":"nouvelle"}},"itemTemplate":{"id":1,"name":"Carte régulière"}},{"referredContent":{"$type":"RC.Neuro.Dtos.v1.NewsStorySummary, RC.Neuro.Dtos","contentType":{"id":"11","name":"Nouvelle"},"id":"1832455","globalId":"11-1832455","canonicalWebLink":{"href":"http://ici.radio-canada.ca/nouvelle/1832455/vacination-quebec-dose-test-depistage-remuneration"},"kicker":"","outOfContextTitle":"Les travailleurs de la santé non vaccinés ne seront plus payés pour être testés trois fois par semaine, décide le gouvernement du Québec","title":"Les travailleurs de la santé non vaccinés ne seront plus payés pour être testés","summary":"<p>Au Québec, les personnes non vaccinées doivent passer trois tests par semaine pour continuer de travailler.</p>","summaryMultimediaItem":{"$type":"RC.Neuro.Dtos.v1.ConceptualImage, RC.Neuro.Dtos","contentType":{"id":"19","name":"Image (Picto)"},"alt":"Image floue de travailleurs de la santé dans un corridor d'hôpital.  ","legend":"Les travailleurs de la santé non vaccinés doivent passer trois tests par semaine pour continuer leur emploi.","imageCredits":"OZANKUTSAL","pressAgencies":[{"id":null,"name":"getty images/istockphoto","codeName":"getty images/istockphoto"}],"imageCollection":"","concreteImages":[{"mediaLink":{"href":"https://images.radio-canada.ca/v1/ici-premiere/1x1/personnel-sante-hopital-infirmieres.jpg"},"width":1414,"height":1414,"dimensionRatio":"1:1"},{"mediaLink":{"href":"https://images.radio-canada.ca/v1/ici-premiere/16x9/personnel-sante-hopital-infirmieres.jpg"},"width":2121,"height":1193,"dimensionRatio":"16:9"},{"mediaLink":{"href":"https://images.radio-canada.ca/v1/ici-premiere/17x6/personnel-sante-hopital-infirmieres.jpg"},"width":2121,"height":749,"dimensionRatio":"17:6"},{"mediaLink":{"href":"https://images.radio-canada.ca/v1/ici-premiere/2x3/personnel-sante-hopital-infirmieres.jpg"},"width":943,"height":1414,"dimensionRatio":"2:3"},{"mediaLink":{"href":"https://images.radio-canada.ca/v1/ici-premiere/4x3/personnel-sante-hopital-infirmieres.jpg"},"width":1885,"height":1414,"dimensionRatio":"4:3"},{"mediaLink":{"href":"https://images.radio-canada.ca/v1/ici-premiere/perso/personnel-sante-hopital-infirmieres.jpg"},"width":2121,"height":1414,"dimensionRatio":"perso"}]},"themeTag":{"id":"13","name":"Politique"},"subThemeTags":[{"id":"102","name":"Politique provinciale"},{"id":"518","name":"Coronavirus"},{"id":"80","name":"Santé publique"}],"publishedLastTimeAt":"2021-10-18T16:54:03.605Z","canonicalWebLinkOverride":null,"primaryClassificationTag":{"id":"12","name":"Nouvelle","codeName":"nouvelle"}},"itemTemplate":{"id":1,"name":"Carte régulière"}},{"referredContent":{"$type":"RC.Neuro.Dtos.v1.NewsStorySummary, RC.Neuro.Dtos","contentType":{"id":"11","name":"Nouvelle"},"id":"1832466","globalId":"11-1832466","canonicalWebLink":{"href":"http://ici.radio-canada.ca/nouvelle/1832466/covid-pandemie-bilan-quebec-deces-cas-hospitalisations-18-octobre"},"kicker":"","outOfContextTitle":"Québec recense 410 nouveaux cas de COVID-19 et 5 décès de plus, tandis que les hospitalisations sont demeurées stables par rapport à la veille","title":"Le Québec compte 410&nbsp;nouveaux cas de COVID-19 et 5&nbsp;décès de plus","summary":"<p>Le nombre d&#x27;hospitalisations est demeuré stable.</p>","summaryMultimediaItem":{"$type":"RC.Neuro.Dtos.v1.ConceptualImage, RC.Neuro.Dtos","contentType":{"id":"19","name":"Image (Picto)"},"alt":"Une femme masquée marche sur un trottoir à Montréal.","legend":"Plus de 420 000 personnes ont été infectées par la COVID-19 au Québec depuis le début de la pandémie.\n\n","imageCredits":"Ivanoh Demers","pressAgencies":[{"id":null,"name":"Radio-Canada","codeName":"Radio-Canada"}],"imageCollection":"","concreteImages":[{"mediaLink":{"href":"https://images.radio-canada.ca/v1/ici-info/transit/1x1/stockshots-pour-bilan-du-jour-de-la-covid-19-a-montreal-urbain-urban-lignes-ombres-shadows-economie-economy-pietons-classe-moyenne-foule-photo-prise-a-la-nmrc-radio-canada-a-montreal-quebec-sur-la-pho-35428.jpg"},"width":3551,"height":3551,"dimensionRatio":"1:1"},{"mediaLink":{"href":"https://images.radio-canada.ca/v1/ici-info/transit/16x9/stockshots-pour-bilan-du-jour-de-la-covid-19-a-montreal-urbain-urban-lignes-ombres-shadows-economie-economy-pietons-classe-moyenne-foule-photo-prise-a-la-nmrc-radio-canada-a-montreal-quebec-sur-la-pho-35428.jpg"},"width":5327,"height":2996,"dimensionRatio":"16:9"},{"mediaLink":{"href":"https://images.radio-canada.ca/v1/ici-info/transit/17x6/stockshots-pour-bilan-du-jour-de-la-covid-19-a-montreal-urbain-urban-lignes-ombres-shadows-economie-economy-pietons-classe-moyenne-foule-photo-prise-a-la-nmrc-radio-canada-a-montreal-quebec-sur-la-pho-35428.jpg"},"width":5327,"height":1880,"dimensionRatio":"17:6"},{"mediaLink":{"href":"https://images.radio-canada.ca/v1/ici-info/transit/2x3/stockshots-pour-bilan-du-jour-de-la-covid-19-a-montreal-urbain-urban-lignes-ombres-shadows-economie-economy-pietons-classe-moyenne-foule-photo-prise-a-la-nmrc-radio-canada-a-montreal-quebec-sur-la-pho-35428.jpg"},"width":2367,"height":3551,"dimensionRatio":"2:3"},{"mediaLink":{"href":"https://images.radio-canada.ca/v1/ici-info/transit/4x3/stockshots-pour-bilan-du-jour-de-la-covid-19-a-montreal-urbain-urban-lignes-ombres-shadows-economie-economy-pietons-classe-moyenne-foule-photo-prise-a-la-nmrc-radio-canada-a-montreal-quebec-sur-la-pho-35428.jpg"},"width":4734,"height":3551,"dimensionRatio":"4:3"},{"mediaLink":{"href":"https://images.radio-canada.ca/v1/ici-info/transit/perso/stockshots-pour-bilan-du-jour-de-la-covid-19-a-montreal-urbain-urban-lignes-ombres-shadows-economie-economy-pietons-classe-moyenne-foule-photo-prise-a-la-nmrc-radio-canada-a-montreal-quebec-sur-la-pho-35428.jpg"},"width":5327,"height":3551,"dimensionRatio":"perso"}]},"themeTag":{"id":"8","name":"Santé"},"subThemeTags":[{"id":"80","name":"Santé publique"},{"id":"518","name":"Coronavirus"}],"publishedLastTimeAt":"2021-10-18T16:10:45.305Z","canonicalWebLinkOverride":null,"primaryClassificationTag":{"id":"12","name":"Nouvelle","codeName":"nouvelle"}},"itemTemplate":{"id":1,"name":"Carte régulière"}},{"referredContent":{"$type":"RC.Neuro.Dtos.v1.NewsStorySummary, RC.Neuro.Dtos","contentType":{"id":"11","name":"Nouvelle"},"id":"1832444","globalId":"11-1832444","canonicalWebLink":{"href":"http://ici.radio-canada.ca/nouvelle/1832444/covid-19-ontario-18-octobre-2021-cas-vaccins-mort"},"kicker":"","outOfContextTitle":"L'Ontario recense 373 nouveaux cas de COVID-19 et 2 décès de plus","title":"COVID-19 : 373&nbsp;nouveaux cas et 2&nbsp;décès en Ontario","summary":"<p>La province recense son plus faible nombre de nouveaux cas de coronavirus en cinq jours.</p>","summaryMultimediaItem":{"$type":"RC.Neuro.Dtos.v1.ConceptualImage, RC.Neuro.Dtos","contentType":{"id":"19","name":"Image (Picto)"},"alt":"Un homme emplit une seringue à partir d'une fiole de vaccin.","legend":"L'Ontario a franchi la barre des 83 % de résidents de 12 ans et plus pleinement vaccinés contre la COVID-19.","imageCredits":"Evan Mitsui","pressAgencies":[{"id":null,"name":"Radio-Canada","codeName":"Radio-Canada"}],"imageCollection":"","concreteImages":[{"mediaLink":{"href":"https://images.radio-canada.ca/v1/ici-info/1x1/vaccination-covid-toronto.JPG"},"width":3265,"height":3265,"dimensionRatio":"1:1"},{"mediaLink":{"href":"https://images.radio-canada.ca/v1/ici-info/16x9/vaccination-covid-toronto.JPG"},"width":4898,"height":2755,"dimensionRatio":"16:9"},{"mediaLink":{"href":"https://images.radio-canada.ca/v1/ici-info/17x6/vaccination-covid-toronto.JPG"},"width":4898,"height":1729,"dimensionRatio":"17:6"},{"mediaLink":{"href":"https://images.radio-canada.ca/v1/ici-info/2x3/vaccination-covid-toronto.JPG"},"width":2177,"height":3265,"dimensionRatio":"2:3"},{"mediaLink":{"href":"https://images.radio-canada.ca/v1/ici-info/4x3/vaccination-covid-toronto.JPG"},"width":4353,"height":3265,"dimensionRatio":"4:3"},{"mediaLink":{"href":"https://images.radio-canada.ca/v1/ici-info/perso/vaccination-covid-toronto.JPG"},"width":4898,"height":3265,"dimensionRatio":"perso"}]},"themeTag":{"id":"8","name":"Santé"},"subThemeTags":[{"id":"518","name":"Coronavirus"}],"publishedLastTimeAt":"2021-10-18T17:59:37.177Z","canonicalWebLinkOverride":null,"primaryClassificationTag":{"id":"12","name":"Nouvelle","codeName":"nouvelle"}},"itemTemplate":{"id":1,"name":"Carte régulière"}},{"referredContent":{"$type":"RC.Neuro.Dtos.v1.NewsStorySummary, RC.Neuro.Dtos","contentType":{"id":"11","name":"Nouvelle"},"id":"1831841","globalId":"11-1831841","canonicalWebLink":{"href":"http://ici.radio-canada.ca/nouvelle/1831841/covid-monde-pandemie-coronavirus"},"kicker":"","outOfContextTitle":"De nombreux pays bien vaccinés ont levé la plupart de leurs mesures et acceptent de vivre désormais avec le virus","title":"Vivre avec la COVID-19, un jeu d’équilibre délicat pour les pays qui en font le choix","summary":"<p>Après 18&nbsp;mois de pandémie, plusieurs pays ont décidé désormais de «&nbsp;vivre avec le virus&nbsp;». </p>","summaryMultimediaItem":{"$type":"RC.Neuro.Dtos.v1.ConceptualImage, RC.Neuro.Dtos","contentType":{"id":"19","name":"Image (Picto)"},"alt":"Une statue portant un masque devant une vue de la marina de Singapour.","legend":"Certains pays, comme Singapour, qui ont annoncé qu'ils « vivraient avec la COVID-19 », continuent de voir d'importantes éclosions.","imageCredits":"EDGAR SU","pressAgencies":[{"id":null,"name":"Reuters","codeName":"Reuters"}],"imageCollection":"","concreteImages":[{"mediaLink":{"href":"https://images.radio-canada.ca/v1/ici-info/1x1/covid-singapour.jpeg"},"width":4326,"height":4326,"dimensionRatio":"1:1"},{"mediaLink":{"href":"https://images.radio-canada.ca/v1/ici-info/16x9/covid-singapour.jpeg"},"width":6508,"height":3661,"dimensionRatio":"16:9"},{"mediaLink":{"href":"https://images.radio-canada.ca/v1/ici-info/17x6/covid-singapour.jpeg"},"width":6508,"height":2297,"dimensionRatio":"17:6"},{"mediaLink":{"href":"https://images.radio-canada.ca/v1/ici-info/2x3/covid-singapour.jpeg"},"width":2884,"height":4326,"dimensionRatio":"2:3"},{"mediaLink":{"href":"https://images.radio-canada.ca/v1/ici-info/4x3/covid-singapour.jpeg"},"width":5768,"height":4326,"dimensionRatio":"4:3"},{"mediaLink":{"href":"https://images.radio-canada.ca/v1/ici-info/perso/covid-singapour.jpeg"},"width":6508,"height":4326,"dimensionRatio":"perso"}]},"themeTag":{"id":"8","name":"Santé"},"subThemeTags":[{"id":"518","name":"Coronavirus"},{"id":"173","name":"Europe"},{"id":"151","name":"Asie"},{"id":"80","name":"Santé publique"},{"id":"232","name":"Vaccination"}],"publishedLastTimeAt":"2021-10-17T08:00:20.317Z","canonicalWebLinkOverride":null,"primaryClassificationTag":{"id":"12","name":"Nouvelle","codeName":"nouvelle"}},"itemTemplate":{"id":1,"name":"Carte régulière"}},{"referredContent":{"$type":"RC.Neuro.Dtos.v1.NewsStorySummary, RC.Neuro.Dtos","contentType":{"id":"11","name":"Nouvelle"},"id":"1832421","globalId":"11-1832421","canonicalWebLink":{"href":"http://ici.radio-canada.ca/nouvelle/1832421/covid-19-depistage-rapide-ecoles-personnes-symptomatiques"},"kicker":"","outOfContextTitle":"COVID-19 : Le dépistage rapide serait utile dans les écoles, dit une nouvelle étude","title":"Le dépistage rapide serait utile dans les écoles, dit une nouvelle étude","summary":"<p>Les tests rapides devraient être réservés en priorité aux personnes symptomatiques, estiment les chercheurs.</p>","summaryMultimediaItem":{"$type":"RC.Neuro.Dtos.v1.ConceptualImage, RC.Neuro.Dtos","contentType":{"id":"19","name":"Image (Picto)"},"alt":"Une enfant souriante insère une tige dans sa narine gauche.","legend":"Des élèves prélèvent eux-mêmes des échantillons dans leurs narines pour un test rapide de dépistage  dans une école de Berlin, en Allemagne.","imageCredits":"Axel Schmidt","pressAgencies":[{"id":null,"name":"Reuters","codeName":"Reuters"}],"imageCollection":"","concreteImages":[{"mediaLink":{"href":"https://images.radio-canada.ca/v1/ici-info/1x1/test-depistage-covid-autotest-rapide-ecoles-eleves-enfant-allemagne-covid-19.JPG"},"width":3667,"height":3667,"dimensionRatio":"1:1"},{"mediaLink":{"href":"https://images.radio-canada.ca/v1/ici-info/16x9/test-depistage-covid-autotest-rapide-ecoles-eleves-enfant-allemagne-covid-19.JPG"},"width":5500,"height":3094,"dimensionRatio":"16:9"},{"mediaLink":{"href":"https://images.radio-canada.ca/v1/ici-info/17x6/test-depistage-covid-autotest-rapide-ecoles-eleves-enfant-allemagne-covid-19.JPG"},"width":5500,"height":1941,"dimensionRatio":"17:6"},{"mediaLink":{"href":"https://images.radio-canada.ca/v1/ici-info/2x3/test-depistage-covid-autotest-rapide-ecoles-eleves-enfant-allemagne-covid-19.JPG"},"width":2444,"height":3666,"dimensionRatio":"2:3"},{"mediaLink":{"href":"https://images.radio-canada.ca/v1/ici-info/4x3/test-depistage-covid-autotest-rapide-ecoles-eleves-enfant-allemagne-covid-19.JPG"},"width":4889,"height":3667,"dimensionRatio":"4:3"},{"mediaLink":{"href":"https://images.radio-canada.ca/v1/ici-info/perso/test-depistage-covid-autotest-rapide-ecoles-eleves-enfant-allemagne-covid-19.JPG"},"width":5500,"height":3667,"dimensionRatio":"perso"}]},"themeTag":{"id":"8","name":"Santé"},"subThemeTags":[{"id":"518","name":"Coronavirus"},{"id":"80","name":"Santé publique"}],"publishedLastTimeAt":"2021-10-18T13:50:35.355Z","canonicalWebLinkOverride":null,"primaryClassificationTag":{"id":"12","name":"Nouvelle","codeName":"nouvelle"}},"itemTemplate":{"id":1,"name":"Carte régulière"}},{"referredContent":{"$type":"RC.Neuro.Dtos.v1.NewsStorySummary, RC.Neuro.Dtos","contentType":{"id":"11","name":"Nouvelle"},"id":"1832349","globalId":"11-1832349","canonicalWebLink":{"href":"http://ici.radio-canada.ca/nouvelle/1832349/ottawa-aide-entreprises-particuliers-covid"},"kicker":"","outOfContextTitle":"COVID-19 : Ottawa évalue des programmes d'aide aux entreprises et aux particuliers qui se terminent cette semaine","title":"COVID-19&nbsp;: Ottawa évalue les mesures d’aide pour les entreprises et les particuliers","summary":"<p>La ministre des Finances Chrystia Freeland envisage de mettre fin à certains programmes d&#x27;urgence cet automne.</p>","summaryMultimediaItem":{"$type":"RC.Neuro.Dtos.v1.ConceptualImage, RC.Neuro.Dtos","contentType":{"id":"19","name":"Image (Picto)"},"alt":"Des gens boivent de la bière. ","legend":"Malgré l'allègement de certaines mesures sanitaires, plusieurs entreprises disent avoir encore besoin de l'aide d'Ottawa.","imageCredits":"","pressAgencies":[{"id":null,"name":"iStock","codeName":"iStock"}],"imageCollection":"","concreteImages":[{"mediaLink":{"href":"https://images.radio-canada.ca/v1/ici-premiere/1x1/bar-resto-mesure-sanitaire-allegement-ceml.jpg"},"width":1414,"height":1414,"dimensionRatio":"1:1"},{"mediaLink":{"href":"https://images.radio-canada.ca/v1/ici-premiere/16x9/bar-resto-mesure-sanitaire-allegement-ceml.jpg"},"width":2119,"height":1192,"dimensionRatio":"16:9"},{"mediaLink":{"href":"https://images.radio-canada.ca/v1/ici-premiere/17x6/bar-resto-mesure-sanitaire-allegement-ceml.jpg"},"width":2119,"height":748,"dimensionRatio":"17:6"},{"mediaLink":{"href":"https://images.radio-canada.ca/v1/ici-premiere/2x3/bar-resto-mesure-sanitaire-allegement-ceml.jpg"},"width":943,"height":1414,"dimensionRatio":"2:3"},{"mediaLink":{"href":"https://images.radio-canada.ca/v1/ici-premiere/4x3/bar-resto-mesure-sanitaire-allegement-ceml.jpg"},"width":1885,"height":1414,"dimensionRatio":"4:3"},{"mediaLink":{"href":"https://images.radio-canada.ca/v1/ici-premiere/perso/bar-resto-mesure-sanitaire-allegement-ceml.jpg"},"width":2119,"height":1414,"dimensionRatio":"perso"}]},"themeTag":{"id":"13","name":"Politique"},"subThemeTags":[{"id":"101","name":"Politique fédérale"},{"id":"518","name":"Coronavirus"},{"id":"400","name":"Économie"}],"publishedLastTimeAt":"2021-10-17T23:30:56.211Z","canonicalWebLinkOverride":null,"primaryClassificationTag":{"id":"12","name":"Nouvelle","codeName":"nouvelle"}},"itemTemplate":{"id":1,"name":"Carte régulière"}}],"hasContinuousLineup":true,"hasEditorialLineup":true}